[{"note_id":"6552468500000000330061ef","cover_url":"https://sns-webpic.xhscdn.com/1040g00830re1b9jt1k5g5nn0kqjg8a5n3s4q338?imageView2/2/w/540/format/jpg","note_create_time":1699890780,"last_update_time":1699890822,"price":0,"room_type":0,"keyword":"武汉转租","info":"武汉华夏理工学院旁边关南园一路公寓转租！|押一付一！！！武汉华夏理工学院旁边关南园一路博雅楼公寓转租！！！  "},{"note_id":"6552461a000000000f025517","cover_url":"https://sns-webpic.xhscdn.com/1040g00830re19kp31e005nu0j3og9068010iju0?imageView2/2/w/540/format/jpg","note_create_time":1699890660,"last_update_time":1699890715,"price":1200,"room_type":1,"keyword":"武汉转租","info":"🏠武汉个人转租｜单间独卫！洪山区|个人因放假回家需要转租出去，非中介，1⃣️2⃣️0⃣️0⃣️，环境很好，设施齐全。\n         #  "},{"note_id":"655245960000000032039dbb","cover_url":"https://sns-webpic.xhscdn.com/1040g00830re17j7p1c005p11dad44uelqbvhffo?imageView2/2/w/540/format/jpg","note_create_time":1699890540,"last_update_time":1699890583,"price":950,"room_type":5,"keyword":"武汉转租","info":"武汉杨家湾附近两室一厅找室友|八一花园两室一厅转租其中一个卧室950一个月，湖景房，南北通透阳光房，民水民电，押一付一，室友养了一只猫，有意联系，只找女生"},{"note_id":"6552456e0000000032039cdf","cover_url":"https://sns-webpic.xhscdn.com/1040g2sg30re16vnshg6g5p30bqck5bhlgln48ng?imageView2/2/w/540/format/jpg","note_create_time":1699890540,"last_update_time":1699890542,"price":1000,"room_type":0,"keyword":"武汉转租","info":"东湖景园a区7-1601阳台 1000转租|房子实图实价，没有下架就还在，喜欢的可以联系我。     房没下架就还在。喜欢的直接联系我，彼此方便，容易交流。没有中介费什么乱七八糟的东西，1000块钱 。个人转租，喜欢的联系我，等你。 转租    "},{"note_id":"655244a6000000003103d81c","cover_url":"https://sns-webpic.xhscdn.com/1040g2sg30re13uc5hg004a75t611gc1mqgq2c28?imageView2/2/w/540/format/jpg","note_create_time":1699890300,"last_update_time":1699890342,"price":0,"room_type":4,"keyword":"武汉转租","info":"整一居室转租，无中介费|洪山区金地本座整一居室转租，无中介费，家具齐全，另外赠送一系列配套设施。低价急转，有意者私信。\n价格美丽，小区配套完善，环境优美。附近有小吃街，商场，电影院，地铁，公交，健身房，菜市场，菜鸟驿站等各种配套。     "},{"note_id":"65524346000000001f02cbc8","cover_url":"https://sns-webpic.xhscdn.com/1040g00830re0ujgkhe6g5otjqtf98fu9brb1f48?imageView2/2/w/540/format/jpg","note_create_time":1699889940,"last_update_time":1699889991,"price":90,"room_type":3,"keyword":"武汉转租","info":"主卧带独卫，大衣柜，民用水电，大客厅，有WiFi，家电齐全，地铁7号线附近，90|主卧带独卫，大衣柜，民用水电，大客厅，有WiFi，家电齐全，地铁7号线附近，900，押一付三   "},{"note_id":"65523e67000000003203864d","cover_url":"https://sns-webpic.xhscdn.com/1040g2sg30re09b54hm5g5o94lk5gbmtmdr81860?imageView2/2/w/540/format/jpg","note_create_time":1699888740,"last_update_time":1699888743,"price":0,"room_type":3,"keyword":"武汉转租","info":"武汉汉阳四新汉欣苑主卧带阳台卫生间转租#个人转租 #阳台 #出租房 #地铁 #转|武汉汉阳四新汉欣苑主卧带阳台卫生间转租     "},{"note_id":"65523dd5000000003300ab6c","cover_url":"https://sns-webpic.xhscdn.com/1040g2sg30re09b54hm605o94lk5gbmtm288i810?imageView2/2/w/540/format/jpg","note_create_time":1699888560,"last_update_time":1699888597,"price":0,"room_type":3,"keyword":"武汉转租","info":"武汉汉阳汉欣苑房租转租，主卧带卫生间阳台|武汉汉阳汉欣苑房租转租，主卧带卫生间阳台"},{"note_id":"65523c05000000001701f89e","cover_url":"https://sns-webpic.xhscdn.com/1040g2sg30re028k01e605odhk738dblbd2th3q8?imageView2/2/w/540/format/jpg","note_create_time":1699888080,"last_update_time":1699888133,"price":1050,"room_type":0,"keyword":"武汉转租","info":"#转租 #武汉转租 #光谷软件园转租 #合租 光谷软件园转租，位置在江南家园1期|    光谷软件园转租，位置在江南家园1期7栋1单元3楼，需要的可以联系我看房，月租1050，免水费，电费民电平摊，房子很大，有个大沙发，有一面壁柜，容量很大，换工作了转租，女生自住房间很干净，搬走会打扫卫生，转租签好之后我能当天搬走 "},{"note_id":"65523bdc000000003203ba00","cover_url":"https://sns-webpic.xhscdn.com/1040g00830re01ldvhi5g5ogdlsek1gnlb1r6coo?imageView2/2/w/540/format/jpg","note_create_time":1699888080,"last_update_time":1699888093,"price":1800,"room_type":4,"keyword":"武汉转租","info":"武汉求租！！！|求租：一室一厅一厨一卫一阳台\n位置：梅苑小区、宝通寺、中南路、洪山广场、楚河汉街地铁沿线都可\n预算：1800以内\n入住时间：11月底左右\n房间要求：民水民电，带电梯。一居室也可，但做饭的地方和卧室最好隔开，最好带阳台有晾衣服的地方。\n支付方式：最好是押一付一\n不太想出中介费，最好是房东直租或转租！！！\n   "},{"note_id":"65523841000000001b0368a7","cover_url":"https://sns-webpic.xhscdn.com/1040g00830rdvji271e6g49v58mqrpdjgbrps01o?imageView2/2/w/540/format/jpg","note_create_time":1699887120,"last_update_time":1699887170,"price":0,"room_type":0,"keyword":"武汉转租","info":"转租，两室一厅次卧，可短租|地址:十里玫瑰二期六栋   离十里铺地铁站900米，王家湾1km\n两室一厅现在室友搬走，寻找爱干净的小姐姐一名，短租一两个月都可以，好商量，厨房客厅家用电器厨具都齐全，可以用，用完洗干净归位就好。 "},{"note_id":"6552c277000000003103ee92","cover_url":"https://sns-webpic.xhscdn.com/1040g00830regfcukhm005o0mnps096m9g83oo90?imageView2/2/w/540/format/jpg","note_create_time":1699922520,"last_update_time":1699922552,"price":0,"room_type":3,"keyword":"武汉转租","info":"武汉光谷广场，主卧，大阳台，转租，包水包物业包上网|武汉光谷广场，主卧，大阳台，转租，包水包物业包上网"},{"note_id":"6552c1ae0000000032036831","cover_url":"https://sns-webpic.xhscdn.com/1040g2sg30regcc77he005nus51h08h0drusirq8?imageView2/2/w/540/format/jpg","note_create_time":1699922340,"last_update_time":1699922351,"price":1200,"room_type":4,"keyword":"武汉转租","info":"个人转租 房东直租 无任何费用|比较着急，随时可以联系看房。\n[位置]:八号线，汪家墩地铁站，小区门口2分钟到地铁站，D出口。鹏程花园。\n[房间]:大概有四十平，一个人住很舒服，带独立卫生间。\n之前是做民宿的，住宿环境好，干净，采光好，东南朝向，通风好，敞亮。\n房间内的，衣柜，沙发，桌子，换鞋架，地毯，都是房东配好的。\n[房租]:直接和房东签合同，房东人好，押一付一，1200一个月。电费自己扫码交费，水费一个月20，包无线网包物业。\n[为什么要转租，我在这住的挺好的其实，楼下有汪家墩夜市，晚上好吃好喝的多，交通也便利，工作调动不能继续租了，所以转租]   "},{"note_id":"6552bb89000000003202a580","cover_url":"https://sns-webpic.xhscdn.com/1040g2sg30refkci5he005o0qveug80hong2hpp0?imageView2/2/w/540/format/jpg","note_create_time":1699920720,"last_update_time":1699920778,"price":800,"room_type":1,"keyword":"武汉转租","info":"古田二路单间转租|直租\n武汉硚口古田二路江边江景房。住房出租一米八大床 ，带独立阳台。卫生间在外面也是独立的。民水民电，交通便利，合租。一个月800元。\n房间全是独立卫生间，互不打扰，房间独立电表，也不用担心电费问题。\n自己转租，没有中介费，直接对接房东。该房源位于滨江军苑"},{"note_id":"6552b7080000000032035364","cover_url":"https://sns-webpic.xhscdn.com/1040g00830ref2pdjhi0049c9uu2pvdr8knde8f0?imageView2/2/w/540/format/jpg","note_create_time":1699919580,"last_update_time":1699919625,"price":900,"room_type":1,"keyword":"武汉转租","info":"900转租！徐东个人单间转租无中介！ 已经搬走随时可看房！ 1.因工作原因，房子|900转租！徐东个人单间转租无中介！\n已经搬走随时可看房！\n1.因工作原因，房子需要转租，不是中介，不收取任何中介费，合同是到明年2月29，首月房租900\n2.房子概括：本房在二楼，房间内都是重新装修过的，是最大的一间房，本人是第一个住的，本人非常爱干净房间内很干净，照片是刚开始住进去时候的样子，房间有一个大阳台，采光很好\n3.位置：徐东友谊大道601号附28号 距离公交地铁步行10分钟 楼下吃的很多 药店水果店超市都有  转租 "},{"note_id":"6552802a0000000032037cee","cover_url":"https://sns-webpic.xhscdn.com/1040g00830re8cesfha004acd9ceadsn3lpksfr0?imageView2/2/w/540/format/jpg","note_create_time":1699905540,"last_update_time":1699905578,"price":0,"room_type":1,"keyword":"武汉转租","info":"虎泉 杨家湾个人转租 武汉租房|虎泉地铁口 领秀城小区单间\n押一付一 民水民电\n安静卫生 采光很好 房间很大 "},{"note_id":"65527def0000000033000f43","cover_url":"https://sns-webpic.xhscdn.com/1040g2sg30re83on9hk005o0g9pk090ckk333d00?imageView2/2/w/540/format/jpg","note_create_time":1699905000,"last_update_time":1699905008,"price":0,"room_type":1,"keyword":"武汉转租","info":"带独卫单间转租|\n华中农业大学旁芷岸龙庭小区，电梯房。11月底搬空，独卫单间，有需要请私聊我。"},{"note_id":"65527d8a000000001b00e5ec","cover_url":"https://sns-webpic.xhscdn.com/1040g2sg30re826q2hk005nnbpsj081mqta8gbtg?imageView2/2/w/540/format/jpg","note_create_time":1699904880,"last_update_time":1699904907,"price":1650,"room_type":5,"keyword":"武汉转租","info":"武汉找室友合租两室一厅|📍地址在 康泰花园海棠苑 距离杨家湾地铁站a口5分钟 交通很方便\n\t\n🏠房子是电梯房 指纹密码锁 家电齐全 生活用品已经全部配齐 只需拎包入住\n\t\n💡我跟朋友租的这个房子 她最近搬走了 我就需要找一个室友一起住\n\t\n🌃房间都有钥匙出门可以锁上 不用担心会有损失 客厅 阳台 公共面积很大 厨房我基本不会用\n\t\n接受情侣入住 水电按人数a ⚠️不能养宠物\n\t\n🔍1650一个月 压一付三 可租半年 水电用多少充多少 无中介费！！！随时可以入住     "},{"note_id":"65527a8d000000003103c986","cover_url":"https://sns-webpic.xhscdn.com/1040g00830re7mhk61k005og24ql8clr7uia9svo?imageView2/2/w/540/format/jpg","note_create_time":1699904100,"last_update_time":1699904141,"price":0,"room_type":4,"keyword":"武汉转租","info":"武汉光谷金地本座一居室转租|电视冰箱空调洗衣机家电一应俱全，超大衣柜，一米八大床，因本人要回老家现在要转租出去，月底到期"},{"note_id":"6552691c000000003200a9bc","cover_url":"https://sns-webpic.xhscdn.com/1040g2sg30re5id9khk004bi198b0pr2uj8hcba0?imageView2/2/w/540/format/jpg","note_create_time":1699899660,"last_update_time":1699899677,"price":0,"room_type":0,"keyword":"武汉转租","info":"武汉光谷自如房子转租，需要的滴滴|周边设施很好，在金地天悦，合租房间有16平，还自带阳台，开窗可以看到南湖，视野很好！还有半年才到期，年底搬家，有需要的姐妹滴滴     "},{"note_id":"655259a30000000017035551","cover_url":"https://sns-webpic.xhscdn.com/1040g2sg30re3lv1a186g5ne1iu608lea87em740?imageView2/2/w/540/format/jpg","note_create_time":1699895700,"last_update_time":1699895715,"price":0,"room_type":6,"keyword":"武汉转租","info":"钟家村地铁 远洋东方境三房转租。无中介费|    \n🏠远洋东方境住宅 三房 首次出租！\n🚄钟家村四六号线换乘，全新家具家电\n❤️自带地暖 中央空调 净水器 清风系统    "},{"note_id":"65525056000000000f02766d","cover_url":"https://sns-webpic.xhscdn.com/1040g00830re2hjoeh8004a50v5j5uf92rdlrhe8?imageView2/2/w/540/format/jpg","note_create_time":1699893300,"last_update_time":1699893334,"price":1200,"room_type":6,"keyword":"武汉转租","info":"个人转租！！！无中介费|因公司要搬走，所以转租，合同到明年8月份，和房东签我剩余合同，小区关南社区四期，电梯房，带阳台，一个月房租1200，三室一厅，水电燃气费均摊，无其他费用，3户共用一卫，仅限女孩子，小区环境很好，离黄龙山地铁站，武汉东站地铁站步行10分钟左右，小区对面就是夜市吃饭很方便[萌萌哒R][萌萌哒R][萌萌哒R]     "},{"note_id":"65524a1f000000001b00c21a","cover_url":"https://sns-webpic.xhscdn.com/1040g2sg30re1o3d9h81g4b7pntu62s3fb3o73g0?imageView2/2/w/540/format/jpg","note_create_time":1699891740,"last_update_time":1699891744,"price":3200,"room_type":0,"keyword":"武汉转租","info":"时代新世界转租|武汉转租 无中介费 3200一月 看了决定好直接和房东签 随时入住"},{"note_id":"6552487c000000003202604f","cover_url":"https://sns-webpic.xhscdn.com/1040g2sg30re1iv6uha6g5n15f66hom38mh08d68?imageView2/2/w/540/format/jpg","note_create_time":1699891320,"last_update_time":1699891324,"price":1100,"room_type":2,"keyword":"武汉转租","info":"光谷华科转租|华科地铁站旁关山大道，琨御府次卧转租1100一个因为租的早所以租金比同小区便宜2-300，拥有40平超大客厅，直接和房东签合同所以也没有中介费和管理费   "},{"note_id":"65504675000000001100c18e","cover_url":"https://sns-webpic.xhscdn.com/1040g00830rc2k9os1kd05p39dl0455kcb24kl50?imageView2/2/w/540/format/jpg","note_create_time":1699759680,"last_update_time":1699876751,"price":0,"room_type":6,"keyword":"武汉转租","info":"香港路转租|香港路三眼桥 3房合租 押一付一 🈚️中介🈚️中介费      "},{"note_id":"6552d42a0000000032007122","cover_url":"https://sns-webpic.xhscdn.com/1040g2sg30reikj94hc605p86snj0hk9n3b4pjp8?imageView2/2/w/540/format/jpg","note_create_time":1699927080,"last_update_time":1699927083,"price":750,"room_type":3,"keyword":"武汉转租","info":"急转，急转，急转，还剩三个月到期|1，转租原因：因为个人原因需要离开武汉\n2，房子地理位置：武汉洪山区柒零社区小区\n3，家电设施：洗衣机，空调，冰箱，天然气，有厨房，可做饭，\n4，水费20月每月，电费0.56元每度，几个租户平摊电费\n5，合租：一共四户，一户女生，一户男生，主卧独卫\n6，楼下有小超市，晚上有很多小食摊摊，快递直接下楼后门就能拿到。\n7，原价转租，不讲价！750/月!!!＃个人转租"},{"note_id":"6552d2af000000003300bae6","cover_url":"https://sns-webpic.xhscdn.com/1040g00830reiepqr1i5g5p8rhgq8sulb6ovhh70?imageView2/2/w/540/format/jpg","note_create_time":1699926660,"last_update_time":1699926703,"price":0,"room_type":1,"keyword":"武汉转租","info":"谁在佛祖岭金融港还没租到房子，个人转租|转租！今天已经搬走\n1.出租原因：因工作调动，房子需要转租出去，不是中介，不收取任何中介费 可以与房东直接签约\n2.房子概括：本房在5楼 电梯房，有大窗户采光效果好，单间带阳台，民水民电\n3.家电设施：新的热水器 空调 桌子 椅子 沙发 冰箱 衣柜 新床 洗衣机 两个人带宠物可以住下\n4.位置：佛祖岭A区 距离佛祖岭地铁口 有轨电车 步行5分钟 楼下有公交车非常方便 适合上班族 楼下超市药店花店附近市场服装店 对面还有医院 商场 小区门口有小吃街         "},{"note_id":"6552cf4c0000000032008062","cover_url":"https://sns-webpic.xhscdn.com/1040g00830rei1isshi005nfrf2jg8ugatatuuh8?imageView2/2/w/540/format/jpg","note_create_time":1699925820,"last_update_time":1699925837,"price":0,"room_type":0,"keyword":"武汉转租","info":"转租|因工作原因紧急转租房子在大花岭地铁站   "},{"note_id":"6552cc7000000000320053c7","cover_url":"https://sns-webpic.xhscdn.com/1040g00830rehdcithm505p20gj94motk4s4v5vg?imageView2/2/w/540/format/jpg","note_create_time":1699925100,"last_update_time":1699925104,"price":0,"room_type":4,"keyword":"武汉转租","info":"个人转租！急急急！！|个人转租不是中介!房子在洪山区文馨街，合租的房子，可以做饭\n①由于工作原因与房东商量后同意转租出去，直接与房东签合同;\n②房子是一居室，家具齐全，冰箱(一级耗\n能)空调洗衣机油烟机都有，民水民电民燃气，水在物业交，电燃气在手机上交，和室友平摊，一个月没多少钱;\n③可押一付一，可转租，房东姐姐人很好;\n④小区环境好，下楼就有早餐店，快递店、药店，楼下有多家24h便利店，买菜(出小区门口就能买)，晚上小区对面还有夜市，不想做饭或者饿了可以来买点吃的!\n⑤出门有两个电梯，不用担心拥挤!\n随时可以看房子!有意联系!中介勿扰谢谢!#武汉#洪山区#租房#转租#短租#长租#武汉\n洪山区租房个人转租房东直租无中介费#两室一厅#整租#合租#租房日常#租房也要幸福#武汉美食#租房武汉 #武汉找工作#武昌区租房#武汉洪\n山区租房职场日常#武汉大学#租房指南#租房"},{"note_id":"6552cc1d000000000f025e35","cover_url":"https://sns-webpic.xhscdn.com/1040g2sg30rehcmn91i305p82k6gkgtq8ve579j0?imageView2/2/w/540/format/jpg","note_create_time":1699924980,"last_update_time":1699925021,"price":0,"room_type":1,"keyword":"武汉转租","info":"三角路地铁口4户两卫一厨单间转租|转租三角路地铁口附近单间带飘窗阳台离地铁口走路两分钟左右4户合租户型4户两卫一厨采光好出勤方便  "},{"note_id":"6552cb660000000032028acb","cover_url":"https://sns-webpic.xhscdn.com/1040g00830rehi9efhg005onej0vnjt51hcfji1o?imageView2/2/w/540/format/jpg","note_create_time":1699924800,"last_update_time":1699924838,"price":1800,"room_type":0,"keyword":"武汉转租","info":"房东直租！！！ 无中介！！！|这是一条转租文案！无中介费！！\n1. 光谷广场  洪福添美  七一七小区 光谷广场广场  立信大厦  光谷步行街  阳光在线 紫菘枫林上城  绿之苑长江职业学院    民族大道  中南民族大学  光谷青年城 湖北开放大学  龙安花苑  当代光谷智慧城  雄楚大道金地雄楚1号 武汉工程大学\n2.随时可以看房子 直租\n3.整租月租1800 可短租月付 民水民电\n4"},{"note_id":"6552ca03000000000f02b3a4","cover_url":"https://sns-webpic.xhscdn.com/1040g00830rehcq671g5g455fe13fp4mqnoa3png?imageView2/2/w/540/format/jpg","note_create_time":1699924440,"last_update_time":1699924947,"price":0,"room_type":0,"keyword":"武汉转租","info":"武汉租房，无中介费|转租啦，没中介费，重新和房东起合同\n·交通便利，门口就公交车站，离地铁站也不远，停车的话车位充足，停车费每月才80块\n·生活便利，楼下很多商超便利店，菜市场生鲜，小吃也很多，离金地广场很近。\n·新装修的，我是首租，很干净很新，精装修\n·最大的优点是房子蛮大，有差不多100坪，两室一客厅一餐厅一厨一卫，还有一个大阳台，一个小储藏间，有个全身镜，南向的，南北通透\n     "},{"note_id":"6552c954000000001b00e472","cover_url":"https://sns-webpic.xhscdn.com/1040g2sg30reha8okhc605om4botmsn3ks9084b8?imageView2/2/w/540/format/jpg","note_create_time":1699924260,"last_update_time":1699924308,"price":0,"room_type":0,"keyword":"武汉转租","info":"店铺转租|无转让费，不用装修，直接上货开业  "},{"note_id":"6552c72a0000000032037ad0","cover_url":"https://sns-webpic.xhscdn.com/1040g00830reh1ph7he4g5n1doao1aipbjsl2f90?imageView2/2/w/540/format/jpg","note_create_time":1699923720,"last_update_time":1699930315,"price":0,"room_type":3,"keyword":"武汉转租","info":"三室一厅一厨一卫，押一付一，无中介费|因为个人工作原因，需要把房子转租出去。地址在杨家湾地铁站附近的南湖锦园小区，转租主卧。三室一厅，另外一个房间一间是一对情侣，一间是一个小姐姐，都是年轻人，都很好相处，也很爱干净，房东也很好。押一付一，无中介费，可短租，民水民电，网费免费，家里另外一个室友有养一只矮脚蓝猫，有意向的可以私聊我哦（出门找的急，房间没来得及收拾，有点乱）     "},{"note_id":"6551b21e000000000f02424c","cover_url":"https://sns-webpic.xhscdn.com/1040g2sg30rdequ5ahg3g5p7vrd8ghmn5ldbbuoo?imageView2/2/w/540/format/jpg","note_create_time":1699852800,"last_update_time":1699883808,"price":900,"room_type":2,"keyword":"武汉转租","info":"武汉转租限女生急藏龙岛附近|      个人转租江夏藏龙岛银河湾三室两厅两卫大次卧\n限一位女生入住 作息规律 租金900包物业 押一付三 网费每月10元 民用水电燃气很便宜 三人均摊\n室友都很好相处作息规律 附近国企上班 步梯5楼 总高6楼 介意勿扰 楼栋不靠近马路小区内里很安静\n租期到明年8月7号 尽量长租万一有变动也是可以转租"},{"note_id":"6552e180000000003300343d","cover_url":"https://sns-webpic.xhscdn.com/1040g00830rek8m6ehk605p7vrd8ghmn59svlbgo?imageView2/2/w/540/format/jpg","note_create_time":1699930440,"last_update_time":1699930496,"price":900,"room_type":2,"keyword":"武汉转租","info":"武汉转租好难救救孩子吧|个人转租限一位女生入住 作息规律的 江夏藏龙岛银河湾三室两厅两卫中的大次卧900包物业不含网费 入住赠送一个季度的网费和燃气费"},{"note_id":"6552e042000000001703613f","cover_url":"https://sns-webpic.xhscdn.com/1040g2sg30rek3qs81m6g5padl02gi75bdtu4mfo?imageView2/2/w/540/format/jpg","note_create_time":1699930140,"last_update_time":1699930178,"price":600,"room_type":0,"keyword":"武汉转租","info":"佛祖岭找室友|佛祖岭B区\n可短租600一个月\n1.可以做饭 有冰箱 有洗衣机等电器\n2.房租可压一付一\n3.民水民电\n "},{"note_id":"6552deac000000003103cdf3","cover_url":"https://sns-webpic.xhscdn.com/1040g2sg30rejtknt18605pa4aq411f25ph0l9e0?imageView2/2/w/540/format/jpg","note_create_time":1699929720,"last_update_time":1699929772,"price":0,"room_type":3,"keyword":"武汉转租","info":"佛祖岭大主卧，阳台，民水民电，交通便利，地铁口，有轨电车，公交站，实拍，短租月付|佛祖岭大主卧，阳台，民水民电，交通便利，地铁口，有轨电车，公交站，实拍，短租月付，     "},{"note_id":"6552de25000000003300b930","cover_url":"https://sns-webpic.xhscdn.com/1040g2sg30rejriif1i605n21fqehvgv5pbej0v8?imageView2/2/w/540/format/jpg","note_create_time":1699929600,"last_update_time":1699929637,"price":650,"room_type":2,"keyword":"武汉转租","info":"有租房需求的姐妹看看我 急急急|    \n【房源位置】武汉东湖高新区九峰明畅里社区2期\n【房租】650元/月，押一付三（无中介费，无物业费）\n【房型】四室一厅一厨两卫，次卧\n【配套设施】洗衣机冰箱空调热水器等基本家用电器一应俱全，可拎包入住\n【水电费用】民水民电，水电燃气与其他三位室友均摊\n【周边环境】附近有光谷生物园地铁站，光谷四路地铁站；小区门口即公交；附近超市医院齐备，便利安全\n【转租原因】本人换工作了\n【合同期限】24.07.03\n【租客要求】限女生，和其他三位室友一起每周轮流打扫卫生\n【备注】离光谷生物城、小米、华为、海康威视等公司都很近"},{"note_id":"6552dc3b0000000032024218","cover_url":"https://sns-webpic.xhscdn.com/1040g00830rejk35p1m0048l86gnfhehj930gq1g?imageView2/2/w/540/format/jpg","note_create_time":1699929120,"last_update_time":1699929555,"price":1600,"room_type":5,"keyword":"武汉转租","info":"光谷one39转租|位置：光谷one39，公交地铁方便，小区交通便利，小区门口就是brt ，离2号线光谷大道近\n租期：明年8月底到期\n月租：1600/月，押一付二\n户型：两室一厅，转租的这间卧室朝南，采光很好\n私聊看房子照片～  "},{"note_id":"6552db66000000001f02e433","cover_url":"https://sns-webpic.xhscdn.com/1040g2sg30rejgrk918005n8klbhk06hd6hfq0b0?imageView2/2/w/540/format/jpg","note_create_time":1699928880,"last_update_time":1699928935,"price":1900,"room_type":4,"keyword":"武汉转租","info":"个人转租！无中介费！|【转租】武汉江岸区，转租整套一居室，8楼有电梯，朝南，可以养宠物，不想扣违约金，急❗️急❗️急❗️（详细视频在空间里）\n【位置】位于江岸区兴业路永红小区B区，紧邻地铁站，距离江汉路25分钟，出行方便，周边生活设施齐全，购物、餐饮俱全。\n【房屋描述】：这是一套全新装修的一居室，面积67平方，家具齐全，家电全新，温馨舒适，适合情侣居住。独立卫生间，独立厨房，独立卧室，独立阳台，独立客厅，生活工作两不误。\n【租金】⚠️月租1900⚠️押一付三⚠️包含物业费。（房东要求，我也没办法）水电费等其他费用为民用，租金支付方季付。\n【租期】目前房屋可随时入住，先来先得呀。\n💡有意者私聊～没有中介费，直接转合同，所有详细信息都说明了，有意者私聊哈。\n      "},{"note_id":"6552dabc000000003203bdce","cover_url":"https://sns-webpic.xhscdn.com/1040g00830reje62fh8005p1u11d3jttgjgjqqu8?imageView2/2/w/540/format/jpg","note_create_time":1699928760,"last_update_time":1699928810,"price":1200,"room_type":4,"keyword":"武汉转租","info":"在武汉！！阳光满屋的感觉太美好|武汉租房地区位于江夏区藏龙东街三和光谷道房租面积30平方独立阳台很宽阔\n交通发达出门二号线附近湖北经济学院武汉传媒学院 光谷青年会小吃街很多价钱1200房东直租房子不收取任何中介费管理费服务费房内有无线网可随时看房私信可约时间       "},{"note_id":"6552da69000000001701df1f","cover_url":"https://sns-webpic.xhscdn.com/1040g00830rejd0bf1m005p9n6n41gnqgo5n5e38?imageView2/2/w/540/format/jpg","note_create_time":1699928640,"last_update_time":1699928682,"price":0,"room_type":0,"keyword":"武汉转租","info":"这么好的阳光房，还不要中介费❗|个人转租，详情看前面作品！  "},{"note_id":"6552da640000000033001e6b","cover_url":"https://sns-webpic.xhscdn.com/1040g2sg30rejctfuhk004a546v1bhvkei7n6k98?imageView2/2/w/540/format/jpg","note_create_time":1699928640,"last_update_time":1699928676,"price":0,"room_type":0,"keyword":"武汉转租","info":"因工作调动去外地。武汉江汉区急转租|没有中介费，位置在汉口火车站附近。   有空调，冰箱，洗衣机。衣服柜子，椅子。可以做饭。民电民水。合租，月付的。"},{"note_id":"6552d9830000000032026b7e","cover_url":"https://sns-webpic.xhscdn.com/1040g2sg30rej9fg6hc005nqorqig96p11jpifo8?imageView2/2/w/540/format/jpg","note_create_time":1699928400,"last_update_time":1699928451,"price":850,"room_type":2,"keyword":"武汉转租","info":"武汉洪山区2号线杨家湾地铁口|武汉洪山区2号线杨家湾地铁口合租单间大次卧转租 压一付一 每月房租850➕30网费  水费全免 电费用多少交多少，我现在每月不超过15   ，痛快的直接免费住20天。\n     "},{"note_id":"6552d96d000000003300a494","cover_url":"https://sns-webpic.xhscdn.com/1040g00830rej94rbhk6g5offmsm41a01hp0h9ao?imageView2/2/w/540/format/jpg","note_create_time":1699928400,"last_update_time":1699928430,"price":0,"room_type":0,"keyword":"武汉转租","info":"急！转租！因实习要离开！特转租！|  房子在紫菘花园，就是光谷广场旁边，近珞雄路地铁站，周围商圈写字楼医院都有，因为我外出实习了，想把房子转租出去，可以续签我的合同到2月份，民水民电，我已经打扫完了，随时可以搬。       "},{"note_id":"6552d92e000000003103f83f","cover_url":"https://sns-webpic.xhscdn.com/1040g00830rej865ghm005nog7bu08mbcs5i6ti0?imageView2/2/w/540/format/jpg","note_create_time":1699928340,"last_update_time":1699928367,"price":85,"room_type":2,"keyword":"武汉转租","info":"#来几个朋友聊聊天 #找合租室友 ◎永红小区B区 个人转租！！！无中介费！ 【转| \n◎永红小区B区\n个人转租！！！无中介费！\n【转租】武汉江岸区，转租次卧，21楼有电梯，朝南，可以养宠物，没什么特殊要求。朋友走了，次卧转出去，没有中介费。\n【位置】位于江岸区兴业路永红小区B区，紧邻地铁站，距离江汉路25分钟，出行方便，周边生活设施齐全，购物、餐饮俱全。\n【房屋描述】：家具齐全，家电全新，温馨舒适，适合情侣居住。生活工作两不误。\n【租金】！月租85”押一付三！包含物业费。\n水电费平摊。租金支付方季付。\n【租期】目前房屋可随时入住，先来先得呀。\n？有意者私聊～没有中介费，直接转合同，所有详细信息都说明了，有意者私聊哈。\n       \n\n𠃋 说点什么•\n⑥2"},{"note_id":"6552d64c000000001701c661","cover_url":"https://sns-webpic.xhscdn.com/1040g00830reiqdae1g1g49s4vk9augpob5r4o5g?imageView2/2/w/540/format/jpg","note_create_time":1699927620,"last_update_time":1699927628,"price":0,"room_type":4,"keyword":"武汉转租","info":"武汉转租-整租无中介（两室一厅）康卓新城|康卓新城转租\n情况:和房东签约一年，2024年02月到期，整租转租免中介费（武汉整租都要中介费的，直接给你免1000！）\n位置:地铁2号线，杨家湾，康卓新城小区（小区装修新，干净简约，是中介口中的网红小区）\n距离2号线（主干线）杨家湾地铁站仅500米（途径汉口火车站，江汉路，洪山广场，街道口，虎泉，光谷广场，武汉东站等重要站点），距光谷广场只一站，交通便利。工作，生活首选！\n环境:白天安静舒适，晚上小区楼下有一排小吃街，夜景很美。烧烤，柠檬水，双皮奶，烤苕皮，总有一款适合你。累了还可以做个美甲，小区美女帅哥多。\n有快递点收发快递方便，附近便利店，早餐店，棋牌室，网咖，药店，小酒馆都有，生活一站式服务配齐，便利多多。\n小区有篮球场，白天有帅气男孩子打球运动。\n小区门口有摩的师傅，上班赶时间优选。\n从地理位置，居住环境，交通环境，和安全角度来看，这个小区是年轻人的优选小区。非常适合对独居有要求的年轻人群。\n房租:押一付一，具体（S）\n房型概况:空间大，带阳台。房间朝南采光好，阳台晒衣服方便不发霉。空气流动性好，通风透气。两室一厅+厨卫，整租。空调，冰箱，洗衣机，网线WIFI，燃气灶都是好的。\n个人因工作原因后面不在洪山区这一块，直接转租，给你免1000中介费。没有中间商赚差价，只想拿回押金，随时可搬！\n\t\n          "},{"note_id":"6552d5ca0000000032009bcb","cover_url":"https://sns-webpic.xhscdn.com/1040g2sg30reiqsgchc005p7eq4e09thqu2je8a8?imageView2/2/w/540/format/jpg","note_create_time":1699927440,"last_update_time":1699927499,"price":950,"room_type":4,"keyword":"武汉转租","info":"光谷杨家湾 柳林雅居 个人转租 可短签月付|1.转租原因:由于个人工作变动，距离公司较远，需要转租出去(本人现在已经搬走，随时看房随时入住\n2.情况概括整栋1层，房屋在7层朝南，视野开阔有阳光，4室合租，目前有2户居住，都是女孩子，正常作息。\n3.家电设施空调、洗衣机，冰箱等家居都有，可以拎包入住\n4.水电网燃气:民水民电电0.588/度(武汉为阶梯式)、水20元一个月随便用、燃气2.53/立方、有网，电燃气均为4户分摊，\n5.地理位置:距离杨家湾光谷地铁口都非常近，小区门口就有公交站，旁边写字楼很多，在光谷那边工作基本在半个小时内都可以到，小区内也有超市、菜市场、菜鸟驿站、药店，生活配置齐全房子我之前租的是950，可以押一付一    "},{"note_id":"6552d5aa0000000032009ae9","cover_url":"https://sns-webpic.xhscdn.com/1040g00830reiqdae1g6049s4vk9augpoe5lj3dg?imageView2/2/w/540/format/jpg","note_create_time":1699927440,"last_update_time":1699927467,"price":0,"room_type":4,"keyword":"武汉转租","info":"武汉租房-直租无中介（两室一厅）康卓新城|康卓新城转租\n情况:和房东签约一年，2024年02月到期，整租转租免中介费（武汉整租都要中介费的，直接给你免1000！）\n位置:地铁2号线，杨家湾，康卓新城小区（小区装修新，干净简约，是中介口中的网红小区）\n距离2号线（主干线）杨家湾地铁站仅500米（途径汉口火车站，江汉路，洪山广场，街道口，虎泉，光谷广场，武汉东站等重要站点），距光谷广场只一站，交通便利。工作，生活首选！\n环境:白天安静舒适，晚上小区楼下有一排小吃街，夜景很美。烧烤，柠檬水，双皮奶，烤苕皮，总有一款适合你。累了还可以做个美甲，小区美女帅哥多。\n有快递点收发快递方便，附近便利店，早餐店，棋牌室，网咖，药店，小酒馆都有，生活一站式服务配齐，便利多多。\n小区有篮球场，白天有帅气男孩子打球运动。\n小区门口有摩的师傅，上班赶时间优选。\n从地理位置，居住环境，交通环境，和安全角度来看，这个小区是年轻人的优选小区。非常适合对独居有要求的年轻人群。\n房租:押一付一，具体（S）\n房型概况:空间大，带阳台。房间朝南采光好，阳台晒衣服方便不发霉。空气流动性好，通风透气。两室一厅+厨卫，整租。空调，冰箱，洗衣机，网线WIFI，燃气灶都是好的。\n个人因工作原因后面不在洪山区这一块，直接转租，给你免1000中介费。没有中间商赚差价，只想拿回押金，随时可搬！\n\t\n         "},{"note_id":"6552d51e000000003202ccc3","cover_url":"https://sns-webpic.xhscdn.com/1040g00830reioaiqhc005ntdcqgg95pmajcn870?imageView2/2/w/540/format/jpg","note_create_time":1699927320,"last_update_time":1699927327,"price":0,"room_type":6,"keyword":"武汉转租","info":"武汉东西湖个人转租|武汉东西湖有没有想租房的小伙伴，小三室一厅一卫一厨。因为失业了要回老家发展，被迫转租。位置在径河街道三店大道沿海赛洛城六期翡丽公馆。诚心租的小伙伴可赠送一个月房租，要看房的话提前联系我  #武汉     "},{"note_id":"6552d40b000000003200707b","cover_url":"https://sns-webpic.xhscdn.com/1040g00830reibfi81g5g5ne1iu608lea49mbcf8?imageView2/2/w/540/format/jpg","note_create_time":1699927020,"last_update_time":1699927052,"price":1600,"room_type":5,"keyword":"武汉转租","info":"转租/一号线🚇头道街 整租 精装两室一厅|转租 一号线🚇头道街 整租精装两室一厅一卫一厨一阳台，超大陆景阳台，采光无敌，1600可刀 欢迎咨询 手慢无   "},{"note_id":"6552d1fe000000000f0274f3","cover_url":"https://sns-webpic.xhscdn.com/1040g00830reic3oohc6g5n8a83641g3hrar1apg?imageView2/2/w/540/format/jpg","note_create_time":1699926480,"last_update_time":1699926527,"price":1100,"room_type":6,"keyword":"武汉转租","info":"武汉东站，黄龙山路合租|地址在天成美景，三室的，整租是3300，平分下来一人一千多，房间还没具体定下来，可看视频\n     "},{"note_id":"6552d16f000000003103e601","cover_url":"https://sns-webpic.xhscdn.com/1040g2sg30rei9tmjhi6g4a763v5vbfoqvbclg2g?imageView2/2/w/540/format/jpg","note_create_time":1699926360,"last_update_time":1699926384,"price":0,"room_type":3,"keyword":"武汉转租","info":"转租主卧 【南湖锦园 】三室一厅一厨一卫|【帮朋友代发】可短租，民水民电，免网费，室友养一只矮脚蓝猫，有意向的可以私聊@💗💗💗\n地址在杨家湾地铁站附近的南湖锦园小区，转租主卧。三室一厅，室友，一对情侣，一个女孩子，很好相处，爱干净，95后        "},{"note_id":"6552d0dc000000001100c644","cover_url":"https://sns-webpic.xhscdn.com/1040g2sg30rei7kep1g005p9b8j5qjfl7ojupl0g?imageView2/2/w/540/format/jpg","note_create_time":1699926180,"last_update_time":1699926236,"price":0,"room_type":0,"keyword":"武汉转租","info":"可短租 可月付 东原启城 无中介|可短租 可月付 东原启城 无中介 民水民电 家电齐全\n随看随住      #"},{"note_id":"6552cd7e000000001b037967","cover_url":"https://sns-webpic.xhscdn.com/1040g2sg30rehqfkg1k6g5ov511l9t4o4qn7u428?imageView2/2/w/540/format/jpg","note_create_time":1699925340,"last_update_time":1699925374,"price":0,"room_type":0,"keyword":"武汉转租","info":"你确定？这都不冲？|新阳广场loft户型\n汉阳万达广场旁边\n三号线地铁四新大道\n小姐姐转租     "},{"note_id":"6552eedc00000000320006e6","cover_url":"https://sns-webpic.xhscdn.com/1040g00830relsr691a605pa3n3ighokot8rf1jo?imageView2/2/w/540/format/jpg","note_create_time":1699933860,"last_update_time":1699933917,"price":0,"room_type":3,"keyword":"武汉转租","info":"转租，佛祖岭G区主卧独卫|帮租户转租佛祖岭G区独卫房，实图实价不会发网图骗你去看房，在这里住过的都知道性价比很高🏠位于佛祖岭G区11楼精装修电梯房密码锁，合同还剩下半年，到期了可以续签：带有公用厨房可做饭；室友都是小姐姐；🉑养宠物，喜欢叫的不允许哦；小区对面就是同心生活广场吃的喝的都有；小区安保方面很完善，24小时物业值班巡逻；出小区就有公交站台共享单车，距离佛祖岭地铁口也就10分钟左右            #武汉传媒学院     "},{"note_id":"6552eeb3000000001b0359e5","cover_url":"https://sns-webpic.xhscdn.com/1040g00830rels7tj1m605p20gj94motktsmq7f8?imageView2/2/w/540/format/jpg","note_create_time":1699933860,"last_update_time":1699933875,"price":0,"room_type":4,"keyword":"武汉转租","info":"个人转租！急急急|个人转租不是中介!房子在洪山区文馨街，合租的房子，可以做饭\n①由于工作原因与房东商量后同意转租出去，直接与房东签合同;\n②房子是一居室，家具齐全，冰箱(一级耗\n能)空调洗衣机油烟机都有，民水民电民燃气，水在物业交，电燃气在手机上交，和室友平摊，一个月没多少钱;\n③可押一付一，可转租，房东姐姐人很好;\n④小区环境好，下楼就有早餐店，快递店、药店，楼下有多家24h便利店，买菜(出小区门口就能买)，晚上小区对面还有夜市，不想做饭或者饿了可以来买点吃的!\n⑤出门有两个电梯，不用担心拥挤!\n随时可以看房子!有意联系!中介勿扰谢谢!#武汉#洪山区#租房#转租#短租#长租#武汉\n洪山区租房个人转租房东直租无中介费#合租#租房日常#租房也要幸福#武汉美食#租房武汉 #武汉找工作#武昌区租房#武汉洪\n山区租房职场日常#租房指南#租房"},{"note_id":"6552ed05000000000f0256d6","cover_url":"https://sns-webpic.xhscdn.com/1040g00830rellm4l1m5g4altu312pclp963p9d8?imageView2/2/w/540/format/jpg","note_create_time":1699933440,"last_update_time":1699933446,"price":0,"room_type":4,"keyword":"武汉转租","info":"武汉佛祖岭社区一室一厅转租，无中介费|      江夏区佛祖岭社区一室一厅转租，无中介费随时看房，房东直租"},{"note_id":"6552eb9000000000330055bd","cover_url":"https://sns-webpic.xhscdn.com/1040g2sg30relfvhi1c5g5p982a30i0uje24e5a8?imageView2/2/w/540/format/jpg","note_create_time":1699933020,"last_update_time":1699933072,"price":0,"room_type":0,"keyword":"武汉转租","info":"阳光满屋的感觉太美好|武汉武昌阳台转租啦！年底真是不好租呀！希望有缘的你能看到这个贴子。三户🈴租，公厨，哈哈哈，两个女室友都不爱做饭如果你是个爱做饭的女生，那就是专享厨房。居民楼，居家小区，民水民电，也没有管理费。但是服务特别好，有维修，有公区包洁，一点都不需要你超心。   "},{"note_id":"6552eb3b000000003202e112","cover_url":"https://sns-webpic.xhscdn.com/1040g00830relel8jhg005n1cmt11b9uq7sgfj2o?imageView2/2/w/540/format/jpg","note_create_time":1699932960,"last_update_time":1699932988,"price":0,"room_type":6,"keyword":"武汉转租","info":"武汉租房！|有没有需要租房的快点看过来哦！\n1，只要女生！三室一厅的房子，目前有两个女生在住。有公共阳台。\n2，水电平摊，因为本人有事不能继续住则要转租。\n3，小区没有物业费，每个月只需要付房租和水电就行，每个房间都有空调，房间很大，放了两米的床，还空出好大的空间。\n4，有冰箱和洗衣机，采光很好。\n房子在武汉汉阳区万科汉阳国际A区。治安物业都很好！"},{"note_id":"6552eb33000000003300aafc","cover_url":"https://sns-webpic.xhscdn.com/1040g00830relc7gj18605o27d1709eiqh091530?imageView2/2/w/540/format/jpg","note_create_time":1699932960,"last_update_time":1699932980,"price":0,"room_type":0,"keyword":"武汉转租","info":"武汉江汉路64平自助女装店转租|武汉江汉路64平自助女装店转租，刚装修好，烟火巷楼上临近地铁c口，全盘带所有东西转租转让，可做女装工作室，99女装。个人转租无中介费。便宜出。因为个人原因要离开武汉，无暇顾及店面，只能遗憾便宜转租。        "},{"note_id":"6552ea99000000003203151d","cover_url":"https://sns-webpic.xhscdn.com/1040g00830relc7gj186g5o27d1709eiqhqdh520?imageView2/2/w/540/format/jpg","note_create_time":1699932780,"last_update_time":1699932826,"price":0,"room_type":0,"keyword":"武汉转租","info":"武汉江汉路64平自助女装店转租转让|武汉江汉路64平自助女装店转租，刚装修好两个月，烟火巷楼上临近地铁c口，位置优，全盘带所有东西转租转让，可做女装工作室，99女装。       "},{"note_id":"6552ea430000000032036818","cover_url":"https://sns-webpic.xhscdn.com/1040g00830relat62hc605paa9lgj8rn7gt57s3g?imageView2/2/w/540/format/jpg","note_create_time":1699932720,"last_update_time":1699932740,"price":0,"room_type":0,"keyword":"武汉转租","info":"个人转租～无中介费，光谷附近| 因工作的原因，需要将住了两年的房间转租[哭惹R]，房间是自己精心布置的，住的很舒适，空间一个人住够用，光线充足，也没有什么噪音，需要看房的宝子们可私聊我哦     "},{"note_id":"6552e7ec00000000330049ce","cover_url":"https://sns-webpic.xhscdn.com/1040g00830rekdgic1i1g4a4bn77703d943gfm7g?imageView2/2/w/540/format/jpg","note_create_time":1699932120,"last_update_time":1699932141,"price":1000,"room_type":0,"keyword":"武汉转租","info":"汉口租房大飘窗采光好带壁柜|    大飘窗采光真的绝了，一天日照时间多久这边全能看到！而且满面墙的大壁柜衣服再多也不怕了～，近地铁长港路，汉口火车站！二号线去哪都方便！租了一年了因为工作原因转租，还剩下半年的租期！ 价格很好1k以内，先到先得！"},{"note_id":"6552e79f000000000f024354","cover_url":"https://sns-webpic.xhscdn.com/1040g2sg30rekvbuehc005nu13ovg94ocopt5nco?imageView2/2/w/540/format/jpg","note_create_time":1699932060,"last_update_time":1699932064,"price":0,"room_type":5,"keyword":"武汉转租","info":"武汉转租，东西湖二雅路loft，两个卧室|房子很不错，刚做完保洁很干净，离地铁也不远，同小区有相同户型的这套算是装修比较好的，但是房租也高，另外我是宗介。   "},{"note_id":"6552e775000000003202d3cd","cover_url":"https://sns-webpic.xhscdn.com/1040g00830rekvupvha005p90m90p2u7rt5kbqr8?imageView2/2/w/540/format/jpg","note_create_time":1699932000,"last_update_time":1699932021,"price":0,"room_type":4,"keyword":"武汉转租","info":"求租汉阳王家湾附近的房子一室两室都可以|求租汉阳王家湾附近的房子一室两室都可以 要装修好看点的 商品房 不要还建房 有房源的滴滴我  "},{"note_id":"6552e729000000001701c795","cover_url":"https://sns-webpic.xhscdn.com/1040g00830rekspa7hk005pa0ra5hgvjhgn61hsg?imageView2/2/w/540/format/jpg","note_create_time":1699931940,"last_update_time":1699932054,"price":1700,"room_type":0,"keyword":"武汉转租","info":"武汉硚口古田个人转租|不是中介没有中介费，个人转租，民水民电，押一付三1700，位置在古田三路四路中间\n\t\n因为要回老家了才要转的，小区出去就是农贸菜市场，然后便利店超市商场轻轨都挺近的\n "},{"note_id":"6552e550000000003200a0b1","cover_url":"https://sns-webpic.xhscdn.com/1040g00830rekqsj81e0g5p5v9pfl7lp0okdcfn8?imageView2/2/w/540/format/jpg","note_create_time":1699931460,"last_update_time":1699931986,"price":0,"room_type":0,"keyword":"武汉转租","info":"离工作地点太远，通勤时间太长，所以打算转租，中南路转租#个人转租 #武汉 #中南|离工作地点太远，通勤时间太长，所以打算转租，中南路转租   "},{"note_id":"6552e54500000000320074a0","cover_url":"https://sns-webpic.xhscdn.com/1040g00830reknd1f1c505o0eg8n09350rlbs6o8?imageView2/2/w/540/format/jpg","note_create_time":1699931460,"last_update_time":1699931461,"price":0,"room_type":0,"keyword":"武汉转租","info":"大学生实习结束，提前回家过年，转自住房|转保利时代全女生房子，开学回学校上学了小区在保利时代，因为开学要回学校上学了，小区门口就是电竞馆，大排档，对面有有一个很大的生鲜超市，位置特别居中，去软件园，旁边挨着k11，楼下吃饭也便利，我就在华科这边，看房给我发消息就行             "},{"note_id":"6552e4080000000033007d1a","cover_url":"https://sns-webpic.xhscdn.com/1040g2sg30rekiikn1g004b6a6oic4p8jdpg2mog?imageView2/2/w/540/format/jpg","note_create_time":1699931100,"last_update_time":1699931144,"price":0,"room_type":4,"keyword":"武汉转租","info":"在武汉找个一室一厅的房子太难了🫤|  有没有一室一厅的房租转租啊。给三只猫腾个空间玩耍啊～"},{"note_id":"6552e2dd0000000033007840","cover_url":"https://sns-webpic.xhscdn.com/1040g00830rekdvvg1c405o2s91gg81ql1mfpdvg?imageView2/2/w/540/format/jpg","note_create_time":1699930800,"last_update_time":1699930846,"price":1555,"room_type":4,"keyword":"武汉转租","info":"武汉光谷独卫独阳转租|个人光谷转租，非中介。想换一居室，巴黎豪庭转租，光谷大道地铁站B出口小区，近地铁，距离华科大很近，独卫独阳，大壁柜，实体墙，朝南通风好，家具齐全，民水民电，空间大。小区环境很好，绿化很好，电梯房。全是女生，仅限女生。1555一个月(原价1600已砍价的)         "},{"note_id":"6552e2980000000032025d02","cover_url":"https://sns-webpic.xhscdn.com/1040g00830rekcsdehg005n12rne1dgc4amkck30?imageView2/2/w/540/format/jpg","note_create_time":1699930740,"last_update_time":1699930880,"price":0,"room_type":2,"keyword":"武汉转租","info":"光谷转租|上岸了，不干了回家，清江山水3期转租大次卧，房间很大，价格便宜，楼下是大湖泊   "},{"note_id":"6552e2760000000033003c5f","cover_url":"https://sns-webpic.xhscdn.com/1040g00830rekcdpb1e505p4ia2eqp0ni9i4n9fg?imageView2/2/w/540/format/jpg","note_create_time":1699930740,"last_update_time":1699930743,"price":0,"room_type":0,"keyword":"武汉转租","info":"姚家岭全女生转租|位置在姚家岭新城，距离小龟山螃蟹岬地铁都很近，电梯房可以做饭。全女生合租＃武汉       "},{"note_id":"6552fd8e0000000032037b34","cover_url":"https://sns-webpic.xhscdn.com/1040g2sg30renm5i5he5g5p56r9npepnh32ms9n0?imageView2/2/w/540/format/jpg","note_create_time":1699937640,"last_update_time":1699937678,"price":1200,"room_type":3,"keyword":"武汉转租","info":"光谷软件园清江山水主卧独卫1200转租|工作变动，忍痛割爱[失望R]看中当天可搬走，押一付一租的，租期还有10个月！    "},{"note_id":"6552fbfc000000000f025339","cover_url":"https://sns-webpic.xhscdn.com/1040g2sg30relkj1lhk305orgq218t81uahloml8?imageView2/2/w/540/format/jpg","note_create_time":1699937220,"last_update_time":1699937276,"price":0,"room_type":0,"keyword":"武汉转租","info":"转租最后一天，刷不到的可惜了|转租最后一天，不要中介费物业费，押金不要或赠一个月房租，租期到明年六月份，交通出行方便，最后一天租不到的后悔去吧，    "},{"note_id":"6552fae7000000003203aca0","cover_url":"https://sns-webpic.xhscdn.com/1040g2sg30renbsdche005p627hgl75jge5r91t8?imageView2/2/w/540/format/jpg","note_create_time":1699936980,"last_update_time":1699936999,"price":1400,"room_type":0,"keyword":"武汉转租","info":"1400压一付一 无中介费 到24年4.1号|     个人转租 不是中介 徐东地铁站附近 生活很方便"},{"note_id":"6552fabf000000001701ccb2","cover_url":"https://sns-webpic.xhscdn.com/1040g00830renappq18005nv2ku3g834osl2ets0?imageView2/2/w/540/format/jpg","note_create_time":1699936920,"last_update_time":1699938893,"price":0,"room_type":0,"keyword":"武汉转租","info":"个人转租❗️❗️❗️❗️|个人转租 ❗️❗️❗️❗️个人转租❗️❗️❗️❗️急急急个人转❗️❗️❗️❗️急急急这是-一条转租文案\n1转租原因:由于个人原因工作变动，需要急着转租出去(目前房租交到11月20号)\n1.转租房子的概况:是个很大的小区，物业绿化做的很棒，本房在电梯21层，采光很好。\n2.家电设施:冰箱，洗衣机，空调，热水器，衣柜\n3.费用;民水民电，押一付一\n4.地理位置:武汉市武昌区瑞景路滨湖·名邸一期(近宝通寺地铁站，马房山地铁站，武商梦时代，附近大学很多)\n5.合同到期时间:2024.7.16(合同到期不租了可以走，也可以续租)中介勿扰!!!\n      "},{"note_id":"6552f8e800000000330052f0","cover_url":"https://sns-webpic.xhscdn.com/1040g2sg30ren25ihhe505p9jbjval7cnr9ahp5o?imageView2/2/w/540/format/jpg","note_create_time":1699936440,"last_update_time":1699936489,"price":650,"room_type":1,"keyword":"武汉转租","info":"转租650/月|急转！武汉理工学院附近，这个房子是我自己租的房子转租。具体位置：武汉市江夏区 庙山保利海上五月花一期，次卧单间，住两人完全没问题，家电水电燃气齐全。650/月，非诚勿扰。"},{"note_id":"6552f8e70000000033009bd4","cover_url":"https://sns-webpic.xhscdn.com/1040g2sg30ren436tha005npbmn7096ukkp6l0io?imageView2/2/w/540/format/jpg","note_create_time":1699936440,"last_update_time":1699936487,"price":0,"room_type":0,"keyword":"武汉转租","info":"#转租 #武汉转租 #个人转租 #租房子 具体详情私聊|    具体详情私聊"},{"note_id":"6552f8930000000032007b44","cover_url":"https://sns-webpic.xhscdn.com/1040g2sg30ren2q4j1i6g5o9i84invcsa7d1k99o?imageView2/2/w/540/format/jpg","note_create_time":1699936380,"last_update_time":1699937135,"price":0,"room_type":0,"keyword":"武汉转租","info":"武汉研口区古田路合租出租房带阳台大卧室|武汉研口区古田路合租出租房带阳台大卧室因实习提前结束，准备转租!房子差不多明年7月10日到期喔电梯房，民水民电，房子出门距地铁口步行5分钟，其他房间合租室友都是女生!!\n仅限女生 ~欢迎咨询我!     "},{"note_id":"6552f86b0000000032039fef","cover_url":"https://sns-webpic.xhscdn.com/1040g2sg30ren25ihhe6g5p9jbjval7cnkqi5s2g?imageView2/2/w/540/format/jpg","note_create_time":1699936320,"last_update_time":1699936364,"price":650,"room_type":1,"keyword":"武汉转租","info":"转租，650/月|急转！武汉理工学院附近，这个房子是我自己租的房子转租。具体位置：武汉市江夏区 庙山保利海上五月花一期，次卧单间，住两人完全没问题，家电水电燃气齐全。650/月，非诚勿扰。"},{"note_id":"6552f83a0000000033000f40","cover_url":"https://sns-webpic.xhscdn.com/1040g2sg30ren1etrhk604btnts6pom2l84dfba0?imageView2/2/w/540/format/jpg","note_create_time":1699936260,"last_update_time":1699936314,"price":0,"room_type":0,"keyword":"武汉转租","info":"年底租房 为什么不找转租啊|谁在武汉还没租到房子啊！！! 转租！短租三个月！！！ 预计11月15号之前搬走。 转租这是一条转租文案. 1.出租原因:由于我个人工作原因，房子需要转租出去，不是中介，不会收取任何中介费哦。 2.转租房子的概括:本房在7楼，电梯房，房间外视野广阔。公卫两人用，阳台外面有平层，平时可以把被子晒外面，环境还可以啦。 3.家电设施:热水空调桌子椅子厨房冰箱衣柜， 4.水电:价格实惠(民水民电)水费每月30元，房间独立电表，合同到期时间(2024年2月12日)转租户主可重新签合同的 5.位置，唐家墩蓝空国粹香舍，小区门口地铁唐家墩6号线，上班出行方便，小区门口有便利店、水果店、早餐店、门口有绿地缤纷城            "},{"note_id":"6552f7cc000000001b00c027","cover_url":"https://sns-webpic.xhscdn.com/1040g00830remvoto1c6049s1fn2vtgh0km61mv0?imageView2/2/w/540/format/jpg","note_create_time":1699936200,"last_update_time":1699936205,"price":0,"room_type":2,"keyword":"武汉转租","info":"实景实拍，个人转租|  转租金地艺境次卧，无中介费，小区近 佛祖岭地铁站，环境比较好 ，电梯房，大壁橱，赠送半个月免费住宿，室友人很好相处，基本上不使用冰箱厨房，生活互不干扰，民电，电费燃气平摊，小区门口吃饭便利，北门出门 可以吃多种小吃。      "},{"note_id":"6552f75b000000003202c681","cover_url":"https://sns-webpic.xhscdn.com/1040g2sg30remtvun1m605nu5shu0bv6ui1l9ha0?imageView2/2/w/540/format/jpg","note_create_time":1699936080,"last_update_time":1699936091,"price":1500,"room_type":0,"keyword":"武汉转租","info":"#武汉租房转租|在思联公馆，离地铁汉口站都比较近，1500/月，跟房东对接"},{"note_id":"6552f6ea0000000033004d2a","cover_url":"https://sns-webpic.xhscdn.com/1040g2sg30remsbai1k005n466rn4f4tf8cbk7a8?imageView2/2/w/540/format/jpg","note_create_time":1699935960,"last_update_time":1699935979,"price":2000,"room_type":4,"keyword":"武汉转租","info":"武汉光谷k11附近求组一居室|保利时代广场周围3公里内 可以养猫 房间干净整洁\n\t\n预算不超过两千 12月中旬左右入住 有12月转租待转租的要出租的可以私聊 因为租房是在12月 中介暂时先不考虑\n    "},{"note_id":"6552f69a00000000320261c0","cover_url":"https://sns-webpic.xhscdn.com/1040g2sg30remr3fdhe005p9ju9oh19scmebftvg?imageView2/2/w/540/format/jpg","note_create_time":1699935840,"last_update_time":1699935899,"price":1000,"room_type":1,"keyword":"武汉转租","info":"个人转租 急转 武铁佳苑|个人转租单间1000可随时联系武汉个人工作原因转租单间1000月\n1.转租原因:\n由于个人工作的原因，需要转租出去\n2、转租房子的概况:\n整栋26层，本房在8楼，房子单间，有单独的洗衣机\n3.家电设:桌子，沙发茶几，衣柜，床，洗衣机，空调，家电设施齐全\n4.水电价格:\n独立电表，水5元/吨，电0.56元/度，房租1000押一付\n5.地理位置:\n位于武汉佳苑 距离地铁站500米，楼下有早餐店，美宜佳，理发店，两百米处有钱大妈，超市，药店等等非常方便  "},{"note_id":"6552f65f0000000032035c42","cover_url":"https://sns-webpic.xhscdn.com/1040g00830remq6dqhe005oemb7s41voo0u8a9og?imageView2/2/w/540/format/jpg","note_create_time":1699935780,"last_update_time":1699935839,"price":1150,"room_type":0,"keyword":"武汉转租","info":"武汉清江山水转租|1150/月    软件园  急转 第一个月可以1000租给你"},{"note_id":"6552f4f90000000032030996","cover_url":"https://sns-webpic.xhscdn.com/1040g2sg30remkmr51m6g5o7teek090jaulhd52g?imageView2/2/w/540/format/jpg","note_create_time":1699935480,"last_update_time":1699935481,"price":1000,"room_type":0,"keyword":"武汉转租","info":"武汉2号线宝通寺地铁个人转租！！|#武汉租房#租房武汉#个人转租无中介费#梅苑小区地铁口～\n目前刚搬走，不过可以随时看房，地址：2号线宝通寺转租，前面一站是中南路，后面一站是街道口，有公交车站，交通十分便利靠近梦时代，亚贸，民水民电 平摊，合租，房间干净，小区环境好，\n一个月 1000带飘窗 还有八个月左右合同，押一付三\n物业费 2块一天（已交）\n其他具体的细节可以联系13797949931这个模板有点东西"},{"note_id":"6552f4430000000033008de0","cover_url":"https://sns-webpic.xhscdn.com/1040g00830remhv3lhg6g5nvb871g9dterhefoq8?imageView2/2/w/540/format/jpg","note_create_time":1699935240,"last_update_time":1699935299,"price":0,"room_type":0,"keyword":"武汉转租","info":"转租！想在武汉安家的朋友看过来！| 房子在光谷广场附近，上一个租客很讲卫生，房子很干净，民水民电，押一付一    "},{"note_id":"6552f4110000000032038a50","cover_url":"https://sns-webpic.xhscdn.com/1040g00830rem82hchc205ns124m09bkcvcjv4ug?imageView2/2/w/540/format/jpg","note_create_time":1699935240,"last_update_time":1699935249,"price":3000,"room_type":5,"keyword":"武汉转租","info":"积玉桥三层楼联投中心转租|联投中心2栋，电梯房，离5号线三层楼地铁站步行7分钟，离2号线积玉桥地铁站隔一个地铁站，离武汉万达中心骑车5分钟，两室一厅一厨一卫，80平，2年前装修，冰箱空调洗衣机家电齐全，房租3000／月（包物业），无中介费。   "},{"note_id":"6552f4010000000033003e71","cover_url":"https://sns-webpic.xhscdn.com/1040g00830relc7gj183g5o27d1709eiqf3gb9t0?imageView2/2/w/540/format/jpg","note_create_time":1699935180,"last_update_time":1699935234,"price":0,"room_type":0,"keyword":"武汉转租","info":"武汉江汉路64平自助女装店转租|武汉江汉路64平自助女装店转租，刚装修好两个月，烟火巷楼上临近地铁c口，全盘带所有东西转租转让，可做女装工作室，99女装。个人原因转租，便宜转出    "},{"note_id":"6552f1cb0000000032008d40","cover_url":"https://sns-webpic.xhscdn.com/1040g00830rem8ai41g005nehsnq0944fr0vrl5o?imageView2/2/w/540/format/jpg","note_create_time":1699934640,"last_update_time":1699934667,"price":0,"room_type":0,"keyword":"武汉转租","info":"光谷软件园个人转租🈚️中介|个人转租！近软件园 民族大道 财经政法大学 app广场 新出精装修 大壁柜 独卫带独立洗衣机 年底特价！\n遇到问题有专业人员解决 🈚️中介！🈚️中介！🈚️中介    "},{"note_id":"6552f1ba000000003202f932","cover_url":"https://sns-webpic.xhscdn.com/1040g00830rem82hchc505ns124m09bkcnsd5bp8?imageView2/2/w/540/format/jpg","note_create_time":1699934640,"last_update_time":1699934920,"price":3000,"room_type":5,"keyword":"武汉转租","info":"积玉桥三层楼租房|联投中心2栋，电梯房，离5号线三层楼地铁站步行7分钟，离2号线积玉桥地铁站隔一个地铁站，离武汉万达中心骑车5分钟，出门即江滩，两室一厅一厨一卫，80平，2年前装修，冰箱空调洗衣机家电齐全，房租3000／月（包物业），无中介费。  "},{"note_id":"6552f023000000003200119f","cover_url":"https://sns-webpic.xhscdn.com/1040g00830rem1qgdhi6g5oj4orrk0ju62nckjtg?imageView2/2/w/540/format/jpg","note_create_time":1699934220,"last_update_time":1699934243,"price":0,"room_type":6,"keyword":"武汉转租","info":"关山高品质小区 千山凌云直租 整租大三房 三室两厅两卫 可分租可整租精装修 随时|关山高品质小区 千山凌云直租\n整租大三房  三室两厅两卫\n可分租可整租精装修\n随时可看  "},{"note_id":"6552ed7300000000320249c8","cover_url":"https://sns-webpic.xhscdn.com/1040g2sg30relncb7hc005ni25gc08vq00e519jo?imageView2/2/w/540/format/jpg","note_create_time":1699933500,"last_update_time":1699933556,"price":0,"room_type":5,"keyword":"武汉转租","info":"求转租！武汉都市泊寓江国路店 两居室|白沙洲江国路店 泊寓。 想转租的可以直接联系我[害羞R][害羞R][害羞R]#      "},{"note_id":"6552ec58000000001100ccdf","cover_url":"https://sns-webpic.xhscdn.com/1040g00830relj2041i6g5nibdnng8a1j2obatdo?imageView2/2/w/540/format/jpg","note_create_time":1699933260,"last_update_time":1699934541,"price":0,"room_type":1,"keyword":"武汉转租","info":"不算转租的#转租|懒得扯皮，直接住，不算转租的  \n1.之前为了不早起租的离公司近的房，最近两月都在家住，所以租房空了将近两月了，空着浪费，直接提前退房东不退房租，还剩下1个半月，所以准备友情价（跳水价）直接找靠谱朋友进来住。\n2.住到我的租房合同到期12.28，要是觉得环境还行可以直接跟房东签，要是觉得环境不满意就是我的合同到期了，我也可以拿到押金，你也可以直接走人。\n3.房屋地点：湖口社区（湖二师旁），大单间独卫，房间隔音不吵，二楼，电梯房\n4.有意向私我，入住日期19-20号都行，可以住到12.28到期，后续是否需要和房东签约继续住看自己满意度"},{"note_id":"65530a720000000017036e0d","cover_url":"https://sns-webpic.xhscdn.com/1040g00830rep8k7ohg004b7pntu62s3f8qon7po?imageView2/2/w/540/format/jpg","note_create_time":1699940940,"last_update_time":1699940978,"price":3200,"room_type":0,"keyword":"武汉转租","info":"武汉时代新世界转租|3200一月 直接和房东签合同 我是转租 不需要你出中介费"},{"note_id":"65530a5a000000003103fd96","cover_url":"https://sns-webpic.xhscdn.com/1040g00830rep87bi1m5g5p9rarjs647iouo7h08?imageView2/2/w/540/format/jpg","note_create_time":1699940940,"last_update_time":1699941038,"price":0,"room_type":0,"keyword":"武汉转租","info":"街道口 2号线地铁口马房山 转租 找室友|    实图 随时可以看房 帖子还在 房子就在圆梦美丽家园"},{"note_id":"65530845000000001703661d","cover_url":"https://sns-webpic.xhscdn.com/1040g00830rep03mghm6g5n19l16hvpd5gfkvbio?imageView2/2/w/540/format/jpg","note_create_time":1699940400,"last_update_time":1699940422,"price":0,"room_type":0,"keyword":"武汉转租","info":"#个人转租 #无中介费 这是--条转租文案 1、 转租原因:由于个人原因工作变动|  这是--条转租文案\n1、 转租原因:由于个人原因工作变动，需要转租出去\n2、转租房子的概况：本房在电梯房14层，独立卫生间，有阳台，有厨房。\n3、家电设施：冰箱，洗衣机，空调，衣柜\n3、费用：有独立电水表，押一付一\n4、地理位置：武汉市洪山区光谷广场街加州阳光1栋(地理位置好，位于光谷步行街意大利风情街附近，下楼走几步有很多好吃的好玩的）"},{"note_id":"655306bb000000003202f26c","cover_url":"https://sns-webpic.xhscdn.com/1040g00830reoq42vhi6g5p843k4gholh10po2gg?imageView2/2/w/540/format/jpg","note_create_time":1699939980,"last_update_time":1699940027,"price":0,"room_type":0,"keyword":"武汉转租","info":"泊寓|武汉艺城泊寓有没有姐妹要转租的，可以马上接手[害羞R]"},{"note_id":"655306b20000000032001b98","cover_url":"https://sns-webpic.xhscdn.com/1040g2sg30reopvg6hi005oes883k0rv0dforao0?imageView2/2/w/540/format/jpg","note_create_time":1699939980,"last_update_time":1699940018,"price":0,"room_type":5,"keyword":"武汉转租","info":"佛祖岭G区两房转租 无中介费|因工作原因 转租佛祖岭G区两房\n房子是电梯房 设备齐全 装修很好 带落地窗\n要求 直接与房东签订合同 压一付三 无中介费（中介勿扰）有想法的可以评论和私聊看房\n\t\n    "},{"note_id":"6553062300000000330049fc","cover_url":"https://sns-webpic.xhscdn.com/1040g2sg30reonp1r186g5nqfj98gbq5fhrs0oqg?imageView2/2/w/540/format/jpg","note_create_time":1699939860,"last_update_time":1699939875,"price":750,"room_type":0,"keyword":"武汉转租","info":"个人低价转租750/月价格可谈|个人转租。中建光谷之星转租\n由于工作调动，个人转租，比较急所以低价转租，无中介费，随时看房,2024年3月1日到期。\n中建光谷之星一楼，合租，15平米，带个阳台，有一户独立卫浴，其他的四户公用一个卫生间，有两户长期出差，环境安静舒适。   "},{"note_id":"655305fa0000000032001a50","cover_url":"https://sns-webpic.xhscdn.com/1040g00830reon5j71c004a7crq7dl0t6ksdt1n8?imageView2/2/w/540/format/jpg","note_create_time":1699939800,"last_update_time":1699939835,"price":1500,"room_type":5,"keyword":"武汉转租","info":"武汉转租|要离开武汉了，转租直接和房东签合同。苗栗路模范新村老小区二楼，两室一厅一卫，有门禁有电梯。是合租，另外一个房间住的两个女生。1500/月季付。离地铁口步行五分钟，楼下吃东西购物很方便，去江汉路很近。视频中为转租房间，房间里大部分家具均是我自己的，布置环境我搬走之后就是空的，看格局就行，公共区域上条小红书里有图  "},{"note_id":"655305680000000032008479","cover_url":"https://sns-webpic.xhscdn.com/1040g00830reoktpu1e005n4qo7i43fdd53k32g8?imageView2/2/w/540/format/jpg","note_create_time":1699939680,"last_update_time":1699939688,"price":0,"room_type":2,"keyword":"武汉转租","info":"武汉光谷超大次卧个人转租|因换城市所以转租出去 面积很大 楼下就是小吃街 风情街 离光谷步行街 地铁站都是几百米 很近 出行方便 剩余燃气费电费全送 有需要的可以联系 15号之前定的可补贴200 急出        "},{"note_id":"655303910000000033007bdf","cover_url":"https://sns-webpic.xhscdn.com/1040g00830reodng1hm005nh6v8mg8k4g2qqir28?imageView2/2/w/540/format/jpg","note_create_time":1699939200,"last_update_time":1699939218,"price":1400,"room_type":4,"keyword":"武汉转租","info":"汉口江汉路吉庆街一室一厅转租|武汉汉口江岸区江汉路吉庆街转租\n基本情况：位置就在吉庆街，看定位，整租，一室一厅，屋内面积蛮大，老小区楼梯房五楼，热水器、冰箱、洗衣机、空调一应俱全，衣服晾在卧室外面可以晒到太阳，楼下就是菜市场、超市、吉庆街，生活非常便利，离江汉路超级近，地铁站循礼门或大智路一公里内，快递楼下拿\n租金：1400/月，一年起租，和房东新签合同，押一付三，民水民电，50块电费俩月了还没用完，无物业费，垃圾费好像是一个月5块\n入住时间：20号之前可入住，想周末搬\n没有中介费，可4️⃣信看房     "},{"note_id":"655303510000000032000cb3","cover_url":"https://sns-webpic.xhscdn.com/1040g00830reocp5u1k004a1aikuupb79ukls698?imageView2/2/w/540/format/jpg","note_create_time":1699939140,"last_update_time":1699939154,"price":3500,"room_type":5,"keyword":"武汉转租","info":"中建大公馆两室一厅3500|个人转租，没有中介费，到24.3，可以短租也可以再续   靠近app，新发展，软件园，保利时代\n\t\n "},{"note_id":"655303010000000032000c07","cover_url":"https://sns-webpic.xhscdn.com/1040g00830reobh5hha6g5ns71qi08p140ojnjeg?imageView2/2/w/540/format/jpg","note_create_time":1699939020,"last_update_time":1699939182,"price":0,"room_type":4,"keyword":"武汉转租","info":"武汉洪山区，一居室转租，独立卧室|武汉洪山区，因工作调动，现转租一室一厅一厨一卫，房屋距离2号线佳园路站500米，在文华学院门口，楼下有生鲜超市，小吃街，生活便利，交通方便。\n价格可详谈# "},{"note_id":"655302e900000000320329ab","cover_url":"https://sns-webpic.xhscdn.com/1040g00830reob5v9ha004bg43ijasi0upih8emo?imageView2/2/w/540/format/jpg","note_create_time":1699939020,"last_update_time":1699939144,"price":7,"room_type":4,"keyword":"武汉转租","info":"🏠房屋个人转租|房子转租半年，由于自己要离开武汉，2024年6月24到期，12月底可以空出来，房租7⃣️，压一付三，四室一厅一卫，冰箱洗衣机都有，水电费四个人平摊，住的全部都是女生，地点在张家湾地铁附近。有意向可以4⃣️[拔草R]    "},{"note_id":"655302cc000000003202ea98","cover_url":"https://sns-webpic.xhscdn.com/1040g00830reoamurhk005n43hif5h1hgm7hu0jo?imageView2/2/w/540/format/jpg","note_create_time":1699939020,"last_update_time":1699944317,"price":0,"room_type":0,"keyword":"武汉转租","info":"找室友|  [蹲R]\n[星R]三室一厅一厨一卫，100平，可挑选其中一间卧室，押一付二\n[星R]民用水电，天然气，可做饭，阳台公用，无顾虑，设施一应俱全，空调，冰箱，电视，Wi-Fi，电梯房，小区底下除了没有电影院，啥吃的喝的都有\n[星R]地铁铁机路站B口，从家步行慢点10分钟，快点78分钟到地铁口，4号线到楚河汉街4站10分钟，途经中南路6站，洪山广场5站，到武昌火车站20分钟，反方向到武汉站6站15分钟，附近最近汽车站杨春湖客运站，小区门口有公交站步行5分钟\n[星R]期望：女生，性格好，爱干净，可养宠物但要照顾好，不带异性朋友回家[微笑R]\n[蹲R]有意者私聊[斜眼R]"},{"note_id":"6553017a000000000f027038","cover_url":"https://sns-webpic.xhscdn.com/1040g2sg30reo5jcihi0g5nst2n10bj0h87mgmlg?imageView2/2/w/540/format/jpg","note_create_time":1699938660,"last_update_time":1699939094,"price":0,"room_type":0,"keyword":"武汉转租","info":"武汉地铁六号线转租 无中介|六号线汉正街转租 无中介 没有中介费 个人转租   "},{"note_id":"6553007f00000000170350d2","cover_url":"https://sns-webpic.xhscdn.com/1040g00830reo1mh81a6g5n2jpdmm6meggc4t91g?imageView2/2/w/540/format/jpg","note_create_time":1699938420,"last_update_time":1699938431,"price":1600,"room_type":1,"keyword":"武汉转租","info":"江汉路个人转租|江汉路500m附近世纪江尚，单间带独卫转租（是合租哈，介意勿扰，房子里加上这个单间一共有五户，有一户马上要搬走了，跟其它租户基本碰不上面，社恐宝宝可以放心的哈)，个人转租无中介费！！！！房间冰箱洗衣机都有。\n因为工作原因需要搬家，低价转租。\n月租我们自己跟房东谈到了1600，押一付三，首月房租可谈（我们自己补贴200-300)有意私信。\n价格美丽，小区配套完善，有电梯（需刷卡)，每栋楼下有保安24小时值班，安全性高，环境优美。附近有小吃街，商场，电影院，地铁，公交，健身房，菜市场，菜鸟驿站等各种配套。      "},{"note_id":"6552fed9000000000f0295b9","cover_url":"https://sns-webpic.xhscdn.com/1040g00830renrabc18005n5musilocfsgts7c78?imageView2/2/w/540/format/jpg","note_create_time":1699938000,"last_update_time":1699938010,"price":955,"room_type":1,"keyword":"武汉转租","info":"武汉转租|1、交通：武汉街道口、马房山地铁附近转租，2号线八号线，离最近地铁站文治街步行12分钟，骑自行车七分钟就到了，小区几百米就有BRT,交通很方便。\n2、小区环境：小区绿化好，扔垃圾拿快递买东西都很方便。\n3、房子情况：单间转租，湖景房，不带独卫，面积大概10平左右，房子整体装修很新，四室两卫，主卧带有独卫，三户公用卫生间，室友男女皆有，年龄都二十多岁，平时基本见不到面，素质都不错，每月有2次保洁，不用担心公区卫生问题，有厨房可以做饭。\n4、价格：955，押一付一，明年5.22到期，到期可续，可以重新签合同。我现在已经搬走，从今天起到11.21可以送你住，注意⚠️是和中介公司签合同，有小程序平台比较有保障，介意勿扰！\n5、室友在都可以看房，我工作在光谷东不太方便，室友可以帮忙开门，想要看房提前告知约时间！\n6、诚心转租！！中国人不骗中国人！这个房子真的特别好，湖景房超级舒服，在床上看南湖，朝南采光也特别好，太阳可以晒到床上，性价比超高，晚上周围也有小吃，我可以推荐给你！要不是换工作根本不想换，超级值相信我！\n最后最后，中介勿扰！！！     "},{"note_id":"6552fe1f000000001b00d278","cover_url":"https://sns-webpic.xhscdn.com/1040g2sg30renof4thm005onej0vnjt51af178ho?imageView2/2/w/540/format/jpg","note_create_time":1699937820,"last_update_time":1699937824,"price":1000,"room_type":0,"keyword":"武汉转租","info":"房东直租！！ 无中介费！！！|1.这是一条转租文案 ！！！\n无中介费！！！\n2. 锦绣良缘  财大小吃街\n3.月租1000 可短租月付\n随时可以看房 急租    "},{"note_id":"6552f4de000000000f027737","cover_url":"https://sns-webpic.xhscdn.com/1040g2sg30rem8ltqhc104a5i0rr63lhj0q2s4uo?imageView2/2/w/540/format/jpg","note_create_time":1699935420,"last_update_time":1699939235,"price":1200,"room_type":0,"keyword":"武汉转租","info":"转租 可做饭的温馨小窝|1⃣️2⃣️0⃣️0⃣️ "},{"note_id":"655319c2000000003202b299","cover_url":"https://sns-webpic.xhscdn.com/1040g2sg30rer2prfhm105ng8t0r08fbsoherpig?imageView2/2/w/540/format/jpg","note_create_time":1699944840,"last_update_time":1699944899,"price":0,"room_type":6,"keyword":"武汉转租","info":"实景实拍| 武汉江夏离永旺800米三室一厅一卫一厨可做饭～"},{"note_id":"65531929000000003202af4b","cover_url":"https://sns-webpic.xhscdn.com/1040g2sg30rer1p5u1i005nbl2nqg8p7u4ho2t3o?imageView2/2/w/540/format/jpg","note_create_time":1699944720,"last_update_time":1699944746,"price":2500,"room_type":6,"keyword":"武汉转租","info":"转租原因：由于个人原因工作变动，需要急着转租 出去（中介也可以帮忙转，真的着急❗|转租原因：由于个人原因工作变动，需要急着转租\n出去（中介也可以帮忙转，真的着急❗️❗️❗️）\n1转租房子的概况:本房在电梯房2层，不是合租，是大三房一厅，厨房跟卫生间都是隔开的，有阳台，采光很好，晾晒衣物都很方便。可以养花草。\n2.家电设施;冰箱，洗衣机，空调，热水器，衣柜，床，电脑桌等\n3,费用：2500包物业民水民电，押一付一\n4.地理位置;武汉市洪山区丽华苑小区 离徐东岳家嘴都近\n5.合同到期时间：2024.5月15号（还有半年，合同到期可以走，也可以续租）中介也可以帮忙转❗️❗️❗️"},{"note_id":"65531872000000003202ad79","cover_url":"https://sns-webpic.xhscdn.com/1040g00830reququ6hi5g5negpvv090fnu4s6q08?imageView2/2/w/540/format/jpg","note_create_time":1699944540,"last_update_time":1699944714,"price":0,"room_type":4,"keyword":"武汉转租","info":"福星惠誉国际城三期|武汉转租正规一室"},{"note_id":"655315ee0000000032001a27","cover_url":"https://sns-webpic.xhscdn.com/1040g00830reqbtl21i005ng7coag829rlrbmtm0?imageView2/2/w/540/format/jpg","note_create_time":1699943880,"last_update_time":1699943919,"price":0,"room_type":0,"keyword":"武汉转租","info":"个人转租个人转租|瑞安府个人转租 急出！！！\n没问题的话当天可入住！\n地点：武汉武昌区瑞安府\n原因:由于工作调动，距离上班地点远故转租\n附近非常方便  公园商场地铁公交都不远\n价格可谈  "},{"note_id":"6553154e000000003202e8da","cover_url":"https://sns-webpic.xhscdn.com/1040g2sg30reqi50qhc005nk76hh08ft7mv14mug?imageView2/2/w/540/format/jpg","note_create_time":1699943700,"last_update_time":1699943758,"price":1400,"room_type":2,"keyword":"武汉转租","info":"光谷软件园光谷App广场附近租房转租|转租：中建大公馆二期（小区入口就在居然之家光谷APP广场正对面，从家出发到光谷APP 广场步行六七分钟），附近有曙光夜市，光谷天地，保利时代广场等商圈\n格局：三室两厅，主卧有独卫，转租次卧，所以卫生间只有两人用，且室友工作时间是错峰使用，不排队，客厅大阳台，晾晒方便，房间有超大飘窗，厨房也只有两人使用，室友使用频率极低，室友和善有事好商量\n房租：1400包物业，无中介费，民水民电天然气自己交，明年六月份到期，还剩半年多\n     "},{"note_id":"6553133b0000000032029f37","cover_url":"https://sns-webpic.xhscdn.com/1040g00830reqatm21e004af7udm3vbmkmbpkvd8?imageView2/2/w/540/format/jpg","note_create_time":1699943220,"last_update_time":1699943228,"price":3000,"room_type":0,"keyword":"武汉转租","info":"武汉金银潭转租 恒大御景 离地铁站200米|月租3000包物业 民水民电 没有家居 有床有空调 差了软装"},{"note_id":"655312c6000000001100fb09","cover_url":"https://sns-webpic.xhscdn.com/1040g00830req94l71g004a55mprh03vbj3af4v8?imageView2/2/w/540/format/jpg","note_create_time":1699943100,"last_update_time":1699943900,"price":1200,"room_type":3,"keyword":"武汉转租","info":"个人转租，中介勿扰|房子在杨家湾南湖锦园，骑车到地铁站五分钟\n三室一厅一厨一卫 现转租主卧\n整面衣柜+化妆台\n民用水电，差不多五毛一度电，水费一季度个人也就十R左右，划重点[暗中观察R]很便宜，目前水电费我都交了，可以接着用，有网，不用额外交网费\n价格：1️⃣2️⃣0️⃣0️⃣/🈷️ 押一付一\n电梯房，21楼，智能门锁\n室友有一对情侣和一个小姐姐，都很好相处，平时大家基本不见面，还有一只矮脚蓝猫，超可爱[派对R]   "},{"note_id":"6553124e000000003200b513","cover_url":"https://sns-webpic.xhscdn.com/1040g00830reoktpu1e3g5n4qo7i43fddbvhm63o?imageView2/2/w/540/format/jpg","note_create_time":1699942980,"last_update_time":1699942991,"price":0,"room_type":2,"keyword":"武汉转租","info":"武汉光谷超大次卧转租|因换城市所以转租出去 面积很大 楼下就是小吃街 风情街 离光谷步行街 地铁站都是几百米 很近 出行方便 剩余燃气费电费全送 有需要的可以联系 15号五点之前定的可补贴200 急出        "},{"note_id":"65530fb10000000032037a03","cover_url":"https://sns-webpic.xhscdn.com/1040g2sg30rept4aohi505p7um11ghk2rk31s868?imageView2/2/w/540/format/jpg","note_create_time":1699942320,"last_update_time":1699942358,"price":0,"room_type":6,"keyword":"武汉转租","info":"租房啦～|个人转租无中介，\n三室一厅好室友。\n公交可直达汉街，\n地铁走路十分钟…\n "},{"note_id":"65530e7c00000000170377d3","cover_url":"https://sns-webpic.xhscdn.com/1040g00830repodgghi005n2lot14au7b092q088?imageView2/2/w/540/format/jpg","note_create_time":1699941960,"last_update_time":1699942013,"price":0,"room_type":0,"keyword":"武汉转租","info":"武汉转租|香港路  "},{"note_id":"65530e67000000001b036d49","cover_url":"https://sns-webpic.xhscdn.com/1040g2sg30repo3bg1m6g5p20gj94motk39a8k2o?imageView2/2/w/540/format/jpg","note_create_time":1699941960,"last_update_time":1699941992,"price":0,"room_type":4,"keyword":"武汉转租","info":"个人转租！超便宜！|个人转租不是中介!房子在洪山区文馨街，合租的房子，可以做饭\n①由于工作原因与房东商量后同意转租出去，直接与房东签合同;\n②房子是一居室，家具齐全，冰箱(一级耗\n能)空调洗衣机油烟机都有，民水民电民燃气，水在物业交，电燃气在手机上交，和室友平摊，一个月没多少钱;\n③可押一付一，可转租，房东姐姐人很好;\n④小区环境好，下楼就有早餐店，快递店、药店，楼下有多家24h便利店，买菜(出小区门口就能买)，晚上小区对面还有夜市，不想做饭或者饿了可以来买点吃的!\n⑤出门有两个电梯，不用担心拥挤!\n随时可以看房子!有意联系!中介勿扰谢谢!#武汉#洪山区#租房#转租#短租#长租#武汉\n洪山区租房个人转租房东直租无中介费#合租#租房日常#租房也要幸福#武汉美食#租房武汉 #武汉找工作#武昌区租房#武汉洪\n山区租房职场日常#租房指南#租房"},{"note_id":"65530d8e000000001100e94c","cover_url":"https://sns-webpic.xhscdn.com/1040g00830repko9n1c004ahah3v8nc8p0pr2qdo?imageView2/2/w/540/format/jpg","note_create_time":1699941720,"last_update_time":1699941830,"price":0,"room_type":0,"keyword":"武汉转租","info":"武汉转租，靠近地铁口，压一付一|独卫带阳台，租期还剩八个月   "},{"note_id":"65530a940000000017036f28","cover_url":"https://sns-webpic.xhscdn.com/1040g2sg30rep941d1a605o528orgbt0r445b60g?imageView2/2/w/540/format/jpg","note_create_time":1699941000,"last_update_time":1699941012,"price":0,"room_type":0,"keyword":"武汉转租","info":"武汉光谷棋牌室转让 310平九个包加一个库房 临街三楼 民水民电 楼下一条餐饮店|武汉光谷棋牌室转让\n310平九个包加一个库房 临街三楼 民水民电 楼下一条餐饮店 旁边万人科技港写字楼 大型社区 对面三个大型酒店\n有需要可联系"},{"note_id":"65530a00000000003203031d","cover_url":"https://sns-webpic.xhscdn.com/1040g2sg30rep6s6218005o5piug084tom9ed9s0?imageView2/2/w/540/format/jpg","note_create_time":1699940820,"last_update_time":1699941060,"price":1160,"room_type":1,"keyword":"武汉转租","info":"个人转租|位置在定位这里（附近app广场新发展软件园红枫a座）\n价格：1160+16网费押一付二，水电燃按户平摊 没有任何服务费之类的\n一楼四户一厨一卫，不用担心安全问题也不潮，自如精装修，当时找朋友直接联系房管谈了很久，不要再问有没有其他服务费隐形费用了，房间22平左右大单间，有意向评论，中介也可，帮忙转付中介费\n\t\n   "},{"note_id":"6553278a00000000330079d2","cover_url":"https://sns-webpic.xhscdn.com/1040g2sg30resq8od1c005nq4le4g97g4a0ncd38?imageView2/2/w/540/format/jpg","note_create_time":1699948380,"last_update_time":1699948427,"price":0,"room_type":0,"keyword":"武汉转租","info":"在武汉｜实景实拍#转租#汉口城市广场#30天|短租！个人转租，房子在汉口城市广场，尚城！交通方便！由于个人原因转租！非常划算！  "},{"note_id":"655326b3000000001701f3c1","cover_url":"https://sns-webpic.xhscdn.com/1040g00830resmvb0hc0049t4mhih9klgsp8h908?imageView2/2/w/540/format/jpg","note_create_time":1699948200,"last_update_time":1699948267,"price":1600,"room_type":0,"keyword":"武汉转租","info":"武汉正街道口京韵花园独卫独阳转租啦！|自己住的转租！无中介费，租期可谈，正街道口位置！\n楼下就是地铁口 独卫独阳1600，物业维修2块/天(包维修)，水费每人每月20，网费每月20（自愿）独立电表一块一度，燃气热水器按人均摊"},{"note_id":"655326a1000000003200b761","cover_url":"https://sns-webpic.xhscdn.com/1040g00830resmgl9ha005o2pb6hg8j93avneps0?imageView2/2/w/540/format/jpg","note_create_time":1699948140,"last_update_time":1699948194,"price":0,"room_type":4,"keyword":"武汉转租","info":"整租一居室转租 无中介费|打算月底转租出去 合同还剩半年 位置就在华科对面\n离二号线华科和光谷大道地铁站只有五百米 楼下就是中百 晚上还有夜市  "},{"note_id":"655325da0000000032039053","cover_url":"https://sns-webpic.xhscdn.com/1040g2sg30resjm1v1c004bur180eposjf35qq6g?imageView2/2/w/540/format/jpg","note_create_time":1699947960,"last_update_time":1699947994,"price":0,"room_type":4,"keyword":"武汉转租","info":"个人转租哦#租房 #押一付一 没有中介费#拎包入住 价格便宜#租房武汉 #一居室|个人转租哦  没有中介费 价格便宜 "},{"note_id":"655323f6000000001f02eae4","cover_url":"https://sns-webpic.xhscdn.com/1040g2sg30resca0hhm605ngv3pj08plq6mf5srg?imageView2/2/w/540/format/jpg","note_create_time":1699947480,"last_update_time":1699947510,"price":0,"room_type":4,"keyword":"武汉转租","info":"个人转租不是中介!房子在洪山区文馨街，合租的房子，可以做饭 ①由于工作原因与房东|个人转租不是中介!房子在洪山区文馨街，合租的房子，可以做饭\n①由于工作原因与房东商量后同意转租出去，直接与房东签合同;\n②房子是一居室，家具齐全，冰箱(一级耗\n能)空调洗衣机油烟机都有，民水民电民燃气，水在物业交，电燃气在手机上交，和室友平摊，一个月没多少钱;\n③可押一付一，可转租，房东姐姐人很好;\n④小区环境好，下楼就有早餐店，快递店、药店，楼下有多家24h便利店，买菜(出小区门口就能买)，晚上小区对面还有夜市，不想做饭或者饿了可以来买点吃的!\n⑤出门有两个电梯，不用担心拥挤!\n随时可以看房子!有意联系!中介勿扰谢谢!#武汉#洪山区#租房#转租#短租#长租#武汉\n洪山区租房个人转租房东直租无中介费#两室一厅#整租#合租#租房日常#租房也要幸福#武汉美食#租房武汉 #武汉找工作#武昌区租房#武汉洪\n山区租房职场日常#武汉大学#租房指南#租房"},{"note_id":"655323eb0000000033008da2","cover_url":"https://sns-webpic.xhscdn.com/1040g00830resc4da1m6g5n4tdrh5md3tg3r11ko?imageView2/2/w/540/format/jpg","note_create_time":1699947480,"last_update_time":1699947499,"price":0,"room_type":4,"keyword":"武汉转租","info":"转租，武汉徐东转租|汪家墩地铁口一居室转租，价好，房好，位置好，适合上班族，有意者私我，"},{"note_id":"655323d200000000330031ca","cover_url":"https://sns-webpic.xhscdn.com/1040g2sg30resbo04hm005n36bt94i4h89mg7m50?imageView2/2/w/540/format/jpg","note_create_time":1699947420,"last_update_time":1699947475,"price":1100,"room_type":6,"keyword":"武汉转租","info":"转租～找一个温柔可爱的室友！|我们是一个小三室，目前有一个室友在12月初到期，因为工作原因不再续租，所以  需要再找一个室友，在关南社区4期，离金融港，武汉东站，光谷天地都非常近，房租1100一个月，没有中介费，如果有需要找房子的小伙伴可以私信我哦，我们都是女孩子，都非常随和，也期待有一个友好和善的室友！"},{"note_id":"6553233e000000000f0271c3","cover_url":"https://sns-webpic.xhscdn.com/1040g2sg30res9gbehe005nl7que09b0vu2o1q90?imageView2/2/w/540/format/jpg","note_create_time":1699947300,"last_update_time":1699947327,"price":1000,"room_type":4,"keyword":"武汉转租","info":"谁在武汉还没有租到房子！！双地铁口|位置：武汉市江岸区市中心 双地铁口\n无需中介费 个人转租 一千出头一居室"},{"note_id":"655323260000000033006ef3","cover_url":"https://sns-webpic.xhscdn.com/1040g2sg30res93rs1c6g5o27d1709eiqublpi2o?imageView2/2/w/540/format/jpg","note_create_time":1699947300,"last_update_time":1699947302,"price":0,"room_type":0,"keyword":"武汉转租","info":"武汉江汉路64平自助女装店转租|刚装修好两个月，烟火巷楼上临近地铁c口，全盘带所有东西转租转让，可做女装工作室，99女装。因为个人原因无法继续待在武汉，特此转让！带店里所有东西转让！      "},{"note_id":"655322fb0000000017034928","cover_url":"https://sns-webpic.xhscdn.com/1040g00830res8ebghm0048sef86umniofbko360?imageView2/2/w/540/format/jpg","note_create_time":1699947240,"last_update_time":1699947259,"price":0,"room_type":0,"keyword":"武汉转租","info":"个人转租 换工作自住房转租 可短租 大学生|个人转租 软件园 世贸中心附近的\n可月付不收中介费 民用水电最便宜那种\n在光谷软件园找房子工作或者想租便宜又好的友友们可以看一下 居住舒适 采光好 带飘窗\n家具家电齐全 有免费wifi 可以拎包入住 光谷天地附近出行很方便  周边生活也很便利 晚上有摆摊小吃街 旁边还有大润发，光谷天地 中百超市 看房联系我        "},{"note_id":"655321ca000000003300bcef","cover_url":"https://sns-webpic.xhscdn.com/1040g00830rerr0k6hk105nnk3s208j8qjh5jrb0?imageView2/2/w/540/format/jpg","note_create_time":1699946940,"last_update_time":1699946955,"price":0,"room_type":0,"keyword":"武汉转租","info":"武汉商务区租房转租近汉口火车站常码头|押一付一 独立卫生间 独立电表\n\t\n楼下小吃超市 近地铁站"},{"note_id":"655321a8000000003300bbb2","cover_url":"https://sns-webpic.xhscdn.com/1040g00830res39kkhg005o375jt08517jkbdqig?imageView2/2/w/540/format/jpg","note_create_time":1699946880,"last_update_time":1699947700,"price":1000,"room_type":4,"keyword":"武汉转租","info":"转租|转租洪山区沙湖港湾B区小一居室，电梯房，靠近4号线园林路和仁和路地铁站，附近有金地自在城商场和永旺，房租1000，合同到明年6月底，11月底可入住     "},{"note_id":"6553218d000000001b0365ac","cover_url":"https://sns-webpic.xhscdn.com/1040g2sg30rern18r1g0g5obema60jbh8fcjo8d8?imageView2/2/w/540/format/jpg","note_create_time":1699946880,"last_update_time":1699946894,"price":0,"room_type":3,"keyword":"武汉转租","info":"转租转租|房子是合租的主卧 有独立阳台卫生间 配有洗衣机 适合情侣居住 卫生间很大 因打算明年回南昌发展了 准备准备回去了 所以不住武汉了 房间内部分东西可以留下来  "},{"note_id":"65531fe90000000017037580","cover_url":"https://sns-webpic.xhscdn.com/1040g00830rersfb91m004bnk95crjn62qoh2aog?imageView2/2/w/540/format/jpg","note_create_time":1699946460,"last_update_time":1699946473,"price":1000,"room_type":2,"keyword":"武汉转租","info":"武汉万松园取水楼地铁口转租|本人因工作原因需要更换租住地方 转租一千多出头 民水民电 小区环境也OK的很 采光特别好 湖景卧室\n小区：天下国际"},{"note_id":"65531f8a000000000f025d8b","cover_url":"https://sns-webpic.xhscdn.com/1040g00830rerr0k6hk005nnk3s208j8qmj80jvo?imageView2/2/w/540/format/jpg","note_create_time":1699946340,"last_update_time":1699946379,"price":1117,"room_type":0,"keyword":"武汉转租","info":"武汉商务区汉口火车站租房转租|押一付一带独立卫生间 独立电表 环境安静  无，中介费用\n价格1117 公共厨房目前没有人用，离地铁站十分钟左右\n  "},{"note_id":"65531f04000000001701cf57","cover_url":"https://sns-webpic.xhscdn.com/1040g2sg30rerjfu81g105nv5t48g8eurckd1k9o?imageView2/2/w/540/format/jpg","note_create_time":1699946220,"last_update_time":1699946244,"price":0,"room_type":4,"keyword":"武汉转租","info":"武汉洪山区转租一居室|   接上一条帖子视频\n个人转租一居室 设备齐全 采光好 床嘎嘎大！任你翻滚\n房东人很好这是真的 啥都好商量\n小区 ：南湖锦城\n地铁（2号线）公交共享单车样样有"},{"note_id":"65531e85000000001f02d37c","cover_url":"https://sns-webpic.xhscdn.com/1040g2sg30rern18r1g005obema60jbh805t1dlo?imageView2/2/w/540/format/jpg","note_create_time":1699946100,"last_update_time":1699946117,"price":0,"room_type":3,"keyword":"武汉转租","info":"武汉市洪山区龙城路南湖社区转租|#   视频后面有详细照片 房子是合租的主卧 有独立阳台卫生间 配有洗衣机 适合情侣居住 卫生间很大 因打算明年回南昌发展了 准备准备回去了 所以不住武汉了 房间内部分东西可以留下来"},{"note_id":"655335a0000000000f027716","cover_url":"https://sns-webpic.xhscdn.com/1040g2sg30reuh9qmhe005o5aeqeg84uf9ptf9ho?imageView2/2/w/540/format/jpg","note_create_time":1699951980,"last_update_time":1699952033,"price":0,"room_type":0,"keyword":"武汉转租","info":"武汉武昌中南路转租|民水民电，空调独卫，中南路地铁口附近，交通便利  "},{"note_id":"65533402000000003202beb6","cover_url":"https://sns-webpic.xhscdn.com/1040g2sg30reuavvn1a505p20gj94motkbkhfhug?imageView2/2/w/540/format/jpg","note_create_time":1699951560,"last_update_time":1699951619,"price":0,"room_type":4,"keyword":"武汉转租","info":"个人转租！！便宜靠谱！|个人转租不是中介!房子在洪山区文馨街，合租的房子，可以做饭\n①由于工作原因与房东商量后同意转租出去，直接与房东签合同;\n②房子是一居室，家具齐全，冰箱(一级耗\n能)空调洗衣机油烟机都有，民水民电民燃气，水在物业交，电燃气在手机上交，和室友平摊，一个月没多少钱;\n③可押一付一，可转租，房东姐姐人很好;\n④小区环境好，下楼就有早餐店，快递店、药店，楼下有多家24h便利店，买菜(出小区门口就能买)，晚上小区对面还有夜市，不想做饭或者饿了可以来买点吃的!\n⑤出门有两个电梯，不用担心拥挤!\n随时可以看房子!有意联系!中介勿扰谢谢!#武汉#洪山区#租房#转租#短租#长租#武汉\n洪山区租房个人转租房东直租无中介费#两室一厅#整租#合租#租房日常#租房也要幸福#武汉美食#租房武汉 #武汉找工作#武昌区租房#武汉洪\n山区租房职场日常#武汉大学#租房指南#租房"},{"note_id":"65533400000000000f026c76","cover_url":"https://sns-webpic.xhscdn.com/1040g00830reuaubj1a005ntoii6g9ajse2pemig?imageView2/2/w/540/format/jpg","note_create_time":1699951560,"last_update_time":1699951616,"price":0,"room_type":0,"keyword":"武汉转租","info":"武汉东站房子转租|整套房子转租\n因工作原因和同事租的二居室租不了了，一大一小两个房间，主卧带阳台，外面有个公共阳台  "},{"note_id":"655330c5000000000f025c2a","cover_url":"https://sns-webpic.xhscdn.com/1040g2sg30reto18ihm504bq8j61lo61d990uju0?imageView2/2/w/540/format/jpg","note_create_time":1699950780,"last_update_time":1699950790,"price":0,"room_type":0,"keyword":"武汉转租","info":"光谷六路，地铁口附近|封闭阳台房，家电齐全，拎包入住，可做饭。   #转租  "},{"note_id":"6553306a0000000032004054","cover_url":"https://sns-webpic.xhscdn.com/1040g00830retsu7k1a5g411ihg4cbr9pf3b45q8?imageView2/2/w/540/format/jpg","note_create_time":1699950660,"last_update_time":1699950699,"price":740,"room_type":6,"keyword":"武汉转租","info":"个人转租 无中介费。|1转租原因: 由于个人工作原因需要转租房子, 不是中介不会收取任何中介费用。\n2楼层在28楼有电梯, 晒衣服窗户外可晒\n3合租房三室一厅一厨一卫\n配套设施: 冰箱、洗衣机、空调、热水器、天然气\n房问情况: 书桌，床，衣柜。\n4.水电: 民用水电, 水电费天然气自己交，平摊；包物业费。\n5.租期: 房租是一个月740,压二付一。\n后续不住转租即可。\n4交通: 文昌路地铁口600米。\n5地理位置: 南湖狮子山街道珞珈雅苑。\n6.女生\n  "},{"note_id":"6553300300000000320240c1","cover_url":"https://sns-webpic.xhscdn.com/1040g2sg30retrbd81e004a75m8hhu8jmlq9cqrg?imageView2/2/w/540/format/jpg","note_create_time":1699950540,"last_update_time":1699950595,"price":1200,"room_type":1,"keyword":"武汉转租","info":"转租！！！谁在武汉需要租房子呀！|无中介费转租！！！预计12月1号前搬走。\n1.转租原因：由于个人原因，房子需要转租出去不是中介，直接和房东签合同，不会收取任何中介费哦。\n2.转租房子的概括：本房在8楼，单间带阳台，电梯房，房间外视野广阔。合租，四室一厅一厨一卫一阳台。环境非常OK啦！\n3.家电设施：天然气空调桌子椅子厨房冰箱衣柜滚筒洗衣机，单间设施一人到两人够用，两个人住一起完全不拥挤所以不用担心。\n4.房租：1200/月，月付，押一付一水电费都是和其他户主平摊的，定期家政打扫公区卫生，很干净！\n5.位置：洪山区金地天悦睿府，24小时保安值班很安全，小区门口有公交车站，离地铁站也很近，，上班出行方便小区门口有便利店水果店餐饮市场超市夜市！！！     "},{"note_id":"65532f90000000000f02a357","cover_url":"https://sns-webpic.xhscdn.com/1040g00830retpjgshc0049t0984ief3505k1jig?imageView2/2/w/540/format/jpg","note_create_time":1699950480,"last_update_time":1699950481,"price":0,"room_type":0,"keyword":"武汉转租","info":"个人转租 急急急 因为个人原因 要离开武汉 房子位于汉口六渡桥景江华亭 独立卫生|个人转租 急急急\n因为个人原因 要离开武汉\n房子位于汉口六渡桥景江华亭 独立卫生间 阳台离江\n汉汉汉汉路600m地铁口 400m 通勤也比较方便 楼下\n24\n小时保安\n月底前就要走了 比较急 有人看上我可以免一部分押金   "},{"note_id":"65532dd30000000033005e28","cover_url":"https://sns-webpic.xhscdn.com/1040g2sg30retiosh1i005ofe6kq8c7sakld7ug8?imageView2/2/w/540/format/jpg","note_create_time":1699950000,"last_update_time":1699951385,"price":2500,"room_type":4,"keyword":"武汉转租","info":"龙湖冠寓杨家湾地铁站店，个人转租|一居室，包物业2500（如果找冠寓官方签要3100+）\n酒店式公寓，民水民电。\n一层7个电梯，上班通勤不用等半天。\n\t\n门禁刷卡、安全性高、物业负责，隔音好。可养宠物。\n缴水电报修什么的都可以直接在app上弄，每月一次入户清洁。\n\t\n楼下就有麦当劳，商圈环境好、种类多、去哪都很方便。\n公寓背面有三个丰巢柜，寄取快递都很方便。\n\t\n离地铁很近，就在街对面。\n  "},{"note_id":"65532d5e000000003202a837","cover_url":"https://sns-webpic.xhscdn.com/1040g00830reth1a2180049f7pnji4toae7jgj48?imageView2/2/w/540/format/jpg","note_create_time":1699949880,"last_update_time":1699952815,"price":0,"room_type":6,"keyword":"武汉转租","info":"3号线转租 三室两卫 无中介费|三室两卫，110平，我是第一任租客，月底可入住，直接跟房东重新签合同，3号线四新大道，保利物业    "},{"note_id":"65532d39000000000f024e0b","cover_url":"https://sns-webpic.xhscdn.com/1040g00830retgadt1e004a01lq54dsamt4arctg?imageView2/2/w/540/format/jpg","note_create_time":1699949880,"last_update_time":1699949881,"price":13,"room_type":4,"keyword":"武汉转租","info":"武汉白沙洲个人转租一居室|押一付一 独门独户 租金13张 没有别的任何费用\n\t\n和房东对接转租\n民水民电 很安静\n附近设施全有 很热闹\n楼下就是小吃一条街"},{"note_id":"65532c0a0000000033000cf3","cover_url":"https://sns-webpic.xhscdn.com/1040g2sg30retbra01g005o7d8m008lc4qc2r3u8?imageView2/2/w/540/format/jpg","note_create_time":1699949520,"last_update_time":1699949579,"price":0,"room_type":3,"keyword":"武汉转租","info":"转租|主卧独卫独阳 岳家嘴地铁口 交通便利   "},{"note_id":"65532bc9000000001701d04e","cover_url":"https://sns-webpic.xhscdn.com/1040g00830retarrfhg005oho7il8c8ju99vjkgg?imageView2/2/w/540/format/jpg","note_create_time":1699949460,"last_update_time":1699949514,"price":0,"room_type":0,"keyword":"武汉转租","info":"个人转租|汉阳人信汇商场楼下，下楼就是地铁口，没有中介费，求租！！  "},{"note_id":"65532b80000000003202ff11","cover_url":"https://sns-webpic.xhscdn.com/1040g00830ret9o4shi004a6sjbamm1mi385fjio?imageView2/2/w/540/format/jpg","note_create_time":1699949400,"last_update_time":1699949441,"price":2100,"room_type":4,"keyword":"武汉转租","info":"光谷一室一厅个人转租|转租！预计 1月10号左右搬走。2100！2100！\n2100！一室一厅！！！\n这是一条转租文案\n1.出租原因：由于我个人原因，房子需要转租出去：\n不是中介，不会收取任何中介费。\n2.转租房子的概括:本房在11楼，电梯房，一室一厅一厨一卫 外独厨 独卫\n3.家电设施:热水器空调桌子沙发厨房冰箱衣柜，标准一室一厅，适合情侣\n4水电：价格实惠(民水民电）\n5.位置：祥和雅居，近二号线佳园路地铁站、公交站，步行10分钟左右，上班出行方便，小区门口有便利店水果店餐饮，门口就文华小吃街，楼下就是乐尔乐超市，买东西便宜且方便     "},{"note_id":"65532b1c000000001b00f509","cover_url":"https://sns-webpic.xhscdn.com/1040g00830ret87ev1i005o8tvtpg96j1jf5pdeg?imageView2/2/w/540/format/jpg","note_create_time":1699949340,"last_update_time":1699949341,"price":1330,"room_type":3,"keyword":"武汉转租","info":"转租主卧|    \n个人！个人！！个人！！！转租 ：\n转租原因：个人工作原因，需要转租，不是中介，可以直接跟房东签约\n地点：杨家湾地铁站附近金地雄楚1号\n电梯房  单间带独卫，厨房公用，目前明年四月份到期，随时可搬\n每月1330（含网，水，物业）月付 无中介费\n小区附近就是金地商圈，吃饭，逛超市，生活非常方便，有意向私聊滴滴"},{"note_id":"65532a87000000003300a88d","cover_url":"https://sns-webpic.xhscdn.com/1040g2sg30ret5u8g1g4g5pag9680htfegtkvccg?imageView2/2/w/540/format/jpg","note_create_time":1699949160,"last_update_time":1699949191,"price":0,"room_type":6,"keyword":"武汉转租","info":"个人转租保利时代|因为下一份工作提供住宿，并且离现在住的地方有些远了，所以思考再三还是决定与这个温馨小窝告别啦，如果你对这个房子的印象还不错可以私聊咨询呀，房子是在保利时代这边的，保利时代这个小区还是很不错的，小区人车分流，里面绿化也很好，晚上在小区里面散步不会被打扰，保利的物业以及智能门锁让居住环境更加安全，小区楼下有很多小吃，靠近南门那边有一个小吃街，每天晚上就会有很多的小吃摊营业，强烈建议去尝一下那个老北京卤肉卷，你从那边走看到排队人最多的那个就是了。这个房间的话并不是很大，但是相应的性价比会很高，三室一厅一卫的合租房住着也不会觉得拥挤，有一个大的客厅和干净整洁的厨房，卫生间是我之前租房的时候特意挑选的蹲厕，水电也是民水民电的，并且这个房子还支持月付哦，马上就要搬走啦，还真有点舍不得，有意向的友友直接私聊我＃房东直租##      #"},{"note_id":"655329290000000032029563","cover_url":"https://sns-webpic.xhscdn.com/1040g2sg30ret0i5r1e6g5obhgo1gje2640s3emo?imageView2/2/w/540/format/jpg","note_create_time":1699948800,"last_update_time":1699948841,"price":1000,"room_type":6,"keyword":"武汉转租","info":"路过的发一张你拍的云|标题：武汉光谷步行街转租1000三室一厅\n由于工作调动现在要搬家，有青山和平公园转租的姐妹也可以联系我。\n位置：光谷步行街风度柏林小区\n租金：1000，电费平摊，包物业费水费\n朝南，采光很好，住了有一年多了，其他两位室友都是小姐姐，人很好，都是一个人在家，工作稳定！生活很便利小区门口就是德意风情街，吃喝玩乐都很方便！"},{"note_id":"655328bc000000001b00edef","cover_url":"https://sns-webpic.xhscdn.com/1040g00830res5el3hi8g5n3gmg4499mmjugcu2o?imageView2/2/w/540/format/jpg","note_create_time":1699948680,"last_update_time":1699949227,"price":0,"room_type":5,"keyword":"武汉转租","info":"武汉两居室转租，设施齐全#租房 #想记录下此刻 #这个模板有点东西 |武汉两居室转租，设施齐全"},{"note_id":"655327ee000000000f02b5c6","cover_url":"https://sns-webpic.xhscdn.com/1040g2sg30resrp4j1c705nl0c97g870keg5bna0?imageView2/2/w/540/format/jpg","note_create_time":1699948500,"last_update_time":1699948527,"price":2000,"room_type":0,"keyword":"武汉转租","info":"江景房转租2k一个月无物业费|   \n武汉音乐学院正对面汉飞又一城转租"},{"note_id":"65532687000000001b03780f","cover_url":"https://sns-webpic.xhscdn.com/1040g00830res5el3hi905n3gmg4499mmtsggr6g?imageView2/2/w/540/format/jpg","note_create_time":1699948140,"last_update_time":1699949257,"price":0,"room_type":5,"keyword":"武汉转租","info":"武汉转租，汤逊湖边两居室#租房 |武汉转租，汤逊湖边两居室"},{"note_id":"65533f62000000000f026a0f","cover_url":"https://sns-webpic.xhscdn.com/1040g2sg30rev9td9hm605n3s0bu5qumebnlmgeg?imageView2/2/w/540/format/jpg","note_create_time":1699954500,"last_update_time":1699954530,"price":0,"room_type":5,"keyword":"武汉转租","info":"佛祖岭G区两房转租 无中介费|因工作原因，转租佛祖岭G区两房\n房子是电梯房，设备齐全，装修很好，带落地窗\n要求，直接与房东签订合同，压一付三，无中介费。（中介勿扰）有想法的可以评论和私聊看房\n    "},{"note_id":"65533e1c000000003203be7e","cover_url":"https://sns-webpic.xhscdn.com/1040g00830revidml1k005ngmlhmg81v7j5v9rj8?imageView2/2/w/540/format/jpg","note_create_time":1699954200,"last_update_time":1699954262,"price":1350,"room_type":5,"keyword":"武汉转租","info":"中南路附近找室友|室友工作原因要搬走了，找一个室友，女孩子哈。\n无中介费请看好条件，非诚勿扰！\n60平小两室\n民水民电，靠近4号线梅苑小区地铁口、2号线中南路，距离梦时代、宝通寺步行15分钟内\n无中介费，下个月可以入住，电梯房。\n房租1350/月，压一付二，水电燃气均摊，无物业费\n小区内什么都有，生活便利，小区内快递驿站、超市、市场什么都有！\n要求：女孩子，不带异性回来，生活作息规律。\n   "},{"note_id":"65533dc3000000001b03674c","cover_url":"https://sns-webpic.xhscdn.com/1040g00830revh2v91a6g5paefcgi08u3a1tmhu8?imageView2/2/w/540/format/jpg","note_create_time":1699954080,"last_update_time":1699954115,"price":0,"room_type":4,"keyword":"武汉转租","info":"转租短租一居室，中南路附近，交通便利|详情看我之前发的笔记    "},{"note_id":"65533d2e000000001100f25e","cover_url":"https://sns-webpic.xhscdn.com/1040g00830revepueh8005o8mimg0bmmhejd5aco?imageView2/2/w/540/format/jpg","note_create_time":1699953960,"last_update_time":1699954084,"price":900,"room_type":0,"keyword":"武汉转租","info":"武汉凯德广场转租|转租没有中介费，江山如画是合租房押一付一900一个月合同是3个月一签，月底交下一次房租。\n这期间我们随时可搬剩余房租免费住！！下楼走3分钟就是凯德广场（6号线就在凯德广场）楼下便利店超市取快递非常方便离一号线骑车几分钟。带阳台可以养小狗和猫咪只要不影响合租室友就行。\n（包宽带物业费，水费电费自己交燃气费25一个月）  "},{"note_id":"65533cd7000000003203b323","cover_url":"https://sns-webpic.xhscdn.com/1040g2sg30revdfim1m005nos5b5094plu9e6jcg?imageView2/2/w/540/format/jpg","note_create_time":1699953840,"last_update_time":1699953880,"price":0,"room_type":6,"keyword":"武汉转租","info":"光谷(湖二师)转租急急急!!! 转租原因:因室友个人原因要离开武汉，房子需要转租|光谷(湖二师)转租急急急!!!\n转租原因:因室友个人原因要离开武汉，房子需要转租出去，不是中介不是中介，三室两厅两卫，厨房用品都有，可拎包入住(都是女孩子，男勿扰)\n采光好，有小的飘窗，干净，小区环境也好，房租押一付一。\n靠近黄龙山隧道，地铁11号线湖口，二号线黄龙山，武汉东站都很近。急租急租"},{"note_id":"65533c9b000000001701d48b","cover_url":"https://sns-webpic.xhscdn.com/1040g00830revcigghc005n12esi1sg69nnu3f30?imageView2/2/w/540/format/jpg","note_create_time":1699953780,"last_update_time":1699953820,"price":1500,"room_type":4,"keyword":"武汉转租","info":"求租直租房不接受中介|预算1500上下，要正规一室一厅整租，不是那种放个沙发就是客厅的，要附近可以坐地铁的地方是3号线2号线和8号线的，要电梯房哈，正常东西都齐全的采光好的，如果价格不高，2室一厅也可以，还有那种自己搞得隔开的那种房子，二手房东的也不要来，不要中介，转租的也可以，有大话联系我"},{"note_id":"65533c59000000001701d3ad","cover_url":"https://sns-webpic.xhscdn.com/1040g00830revbf4hhe005onej0vnjt51pa51pm8?imageView2/2/w/540/format/jpg","note_create_time":1699953720,"last_update_time":1699953753,"price":900,"room_type":0,"keyword":"武汉转租","info":"房东直租！！！ 无中介费！！|这是一条转租文案！！！\n房东直租！！！  无中介费！！！\nSBI光谷创业街\n近华科大 泛悦城 光谷世界城 光谷大道地铁站  金梭花园 琨御府 保利花园\n900可短租月付  首月可减50\n急租 随时可以看房！！   "},{"note_id":"65533bbe000000000f025a8a","cover_url":"https://sns-webpic.xhscdn.com/1040g2sg30rev9680h8005nhrre7g97kk2cfr7no?imageView2/2/w/540/format/jpg","note_create_time":1699953540,"last_update_time":1699953599,"price":1200,"room_type":1,"keyword":"武汉转租","info":"转租！不是中介！！！独卫|独卫转租！不是中介！可短租！\n合租的小伙伴可以看一下，独卫单问！\n∞无中介！无中介！无中介！\n地区：全武汉三环内，离地铁站三百米！！！\n价格：1200\n1没有中介费，代看费，看中就租，当天可立即入住。\n2.公区每月有专门的保洁阿姨做卫生。\n3,今年毕业的应届毕业生，免押金，口元搬家；实习生，半押金。\n4.物品损坏会有专门维修师傅进行处理。\n5.都是多少年轻人，遇到问题都有人负责。\n   \n       \n"},{"note_id":"65533b2a000000001701d127","cover_url":"https://sns-webpic.xhscdn.com/1040g2sg30rev6u3nhe005oo4i023omitpu66el0?imageView2/2/w/540/format/jpg","note_create_time":1699953420,"last_update_time":1699953450,"price":1300,"room_type":4,"keyword":"武汉转租","info":"【转租】2号线佳园路【祥和雅居】公寓一居室|2号线佳园路【祥和雅居】公寓一居室\n价格1300（7栋1单元门左边、公寓牌上2楼）\n不在武汉上班了转租 半年一租还有一个月到期便宜转租 押一付一的房租\n续租需要自己跟房东谈 原价是房租1500 水费30一个月包干 50卫生费 100的网费管理费 一起一个月租金1780\n12月17日半年到期 有需求的可以私聊"},{"note_id":"655337e6000000003300a3a1","cover_url":"https://sns-webpic.xhscdn.com/1040g2sg30reuq5d41e005p7c4i20a45v0v0glbo?imageView2/2/w/540/format/jpg","note_create_time":1699952580,"last_update_time":1699952615,"price":7000,"room_type":0,"keyword":"武汉转租","info":"东原启程转租|东原启城三四期转租个人转租合租  东原启城5号线白沙六路地铁站附近上班方便无中介费  物业费我已经交完了 你不需要交了 月付 押一付一拧包入住家具电器一一俱全有个小落地窗 价格7开头 可以养猫哦转租原因:个人因为离上班的地方比较远 想租一个近一点的房子 可私聊"},{"note_id":"6553358300000000320257b3","cover_url":"https://sns-webpic.xhscdn.com/1040g00830reugrff1c005n3ouaslneah42taq50?imageView2/2/w/540/format/jpg","note_create_time":1699951980,"last_update_time":1699952003,"price":950,"room_type":0,"keyword":"武汉转租","info":"个人转租江汉区范湖地铁距离天街cbd很近，因为工作原因不能继续租下去，房间很大，|个人转租江汉区范湖地铁距离天街cbd很近，因为工作原因不能继续租下去，房间很大，很敞亮，带一个很大的飘窗，住到11月28，下午七点和周末可看房\n房租950一个月 押一付三，管理费已交，水电费和室友平摊，合同到明年7月26"},{"note_id":"65530e2100000000330016cf","cover_url":"https://sns-webpic.xhscdn.com/1040g00830repn0lrhi605opgar05bpai58sip5g?imageView2/2/w/540/format/jpg","note_create_time":1699941900,"last_update_time":1699946316,"price":750,"room_type":5,"keyword":"武汉转租","info":"750 武汉没有人要短租房过渡的吗？|南国都市二期 近武昌工学院 湖北中医药大学 首义学院 万科 天街 地铁五号线\n要实习了不在这边住了 纯个人转租\n短租三个月 二月过后可以整租 两居室   "},{"note_id":"65534cad0000000032037d7d","cover_url":"https://sns-webpic.xhscdn.com/1040g2sg30rf1bbl4h86g4bu82irde7s72nnk8i8?imageView2/2/w/540/format/jpg","note_create_time":1699957920,"last_update_time":1699957934,"price":0,"room_type":1,"keyword":"武汉转租","info":"转租小单间啦！|武汉曙光星城c区房子转租，没有任何中介费[哇R]，民水民电，交通便利，价格也便宜，换工作了所以转租出去[    "},{"note_id":"655347f70000000032025ded","cover_url":"https://sns-webpic.xhscdn.com/1040g2sg30rf0oog31a005n6a5eq49e4p98c75q0?imageView2/2/w/540/format/jpg","note_create_time":1699956720,"last_update_time":1699956727,"price":0,"room_type":1,"keyword":"武汉转租","info":"要回老家了，华科校内单间转租（无中介费）|• 个人转租，无中介费，因个人原因11月中下旬离开武汉，可以与房东直接签约（房东是一位退休老师，人超级好）短租长租都可以（一个月起）\n• 房子概括：华科东三区（中操附近），具体如图2\n•家电家具：如图2。房间内家电家具有空调、床、书柜、衣柜、衣服挂架、桌子椅子\n• 位置：华中科技大学东三区，附近有中操 光谷体育馆游泳馆 南四门 泛悦城\n• 另外出个人用电动车，详情看下一条帖\n "},{"note_id":"655347e4000000000f025911","cover_url":"https://sns-webpic.xhscdn.com/1040g00830rf0nurnhm605p56r9npepnh4lotob8?imageView2/2/w/540/format/jpg","note_create_time":1699956660,"last_update_time":1699956709,"price":1200,"room_type":3,"keyword":"武汉转租","info":"光谷软件园清江山水主卧独卫1200转租|工作变动，忍痛割爱[失望R]看中当天可搬走，押一付一租的，租期还有10个月！    "},{"note_id":"6553479700000000320325e0","cover_url":"https://sns-webpic.xhscdn.com/1040g2sg30rf0nchb1g005p9a355aj9n4pcnkkmo?imageView2/2/w/540/format/jpg","note_create_time":1699956600,"last_update_time":1699956631,"price":0,"room_type":1,"keyword":"武汉转租","info":"合租单间转租|近武昌工学院，五号线光霞地铁站，白沙天街旁\n喜瑞都小区\n四户合租价格便宜，可改合同\n   "},{"note_id":"65533d6d000000003300505f","cover_url":"https://sns-webpic.xhscdn.com/1040g00830revfom91m6g5nf2amgg8ph3hmvoif0?imageView2/2/w/540/format/jpg","note_create_time":1699954020,"last_update_time":1699954570,"price":1950,"room_type":0,"keyword":"武汉转租","info":"武汉江汉路到底有没有人租房啊|转租 1950 价格短租都能商量🥺"},{"note_id":"65536087000000003203adf1","cover_url":"https://sns-webpic.xhscdn.com/1040g2sg30rf3osfchi6g5pageqfgmm835ornf9g?imageView2/2/w/540/format/jpg","note_create_time":1699962960,"last_update_time":1699963016,"price":0,"room_type":3,"keyword":"武汉转租","info":"武汉个人转租｜手机实拍！|🚇武汉地铁8号线\n🎈地标:竹叶山地铁口，金桥永旺梦乐城，中一路隧道\n🏠主卧独卫房\n⭐手机实拍！头像下方有定位！\n        "},{"note_id":"65535d4c0000000033005f23","cover_url":"https://sns-webpic.xhscdn.com/1040g2sg30rf3c5ophi004a7dgu1fbe4o4b5g9vg?imageView2/2/w/540/format/jpg","note_create_time":1699962180,"last_update_time":1699962189,"price":900,"room_type":2,"keyword":"武汉转租","info":"诚意转租 我贴💰行不行！|9百包物业包物业包物业！\n租不了吃亏租不了上当\n已经搬走了随时可以入住！！！\n个人原因离开武汉，不然性价比这么高的房子是不会转的！\n位置在4号线 仁和路地铁口 走路5分钟可以到（实测金地自在城三室一厅一卫一厨大次卧转租 房子全部朝南 采光极好\n民水民电超便宜der室友是00后 好相处有时候还会给我煮东西嘿嘿\n附近有金地广场各种小吃街不远处也有农贸市场\n逛吃逛吃都很方便\n\t\n房子首次出租所以需要很爱干净哦\n        "},{"note_id":"65535492000000000f0248c9","cover_url":"https://sns-webpic.xhscdn.com/1040g2sg30rf2a62fhg304bumi4oe1tvpv20cid0?imageView2/2/w/540/format/jpg","note_create_time":1699959900,"last_update_time":1699959955,"price":0,"room_type":4,"keyword":"武汉转租","info":"急转正规一居室 短租一个月|价格🉑商量 着急转     "},{"note_id":"655354220000000033007dca","cover_url":"https://sns-webpic.xhscdn.com/1040g00830rf28doeh8005n5musilocfs8c1qc0g?imageView2/2/w/540/format/jpg","note_create_time":1699959840,"last_update_time":1699959842,"price":955,"room_type":1,"keyword":"武汉转租","info":"武汉转租|1、交通：武汉街道口、马房山地铁附近转租，2号线八号线，离最近地铁站文治街步行12分钟，骑自行车七分钟就到了，小区几百米就有BRT,交通很方便。\n2、小区环境：小区绿化好，扔垃圾拿快递买东西都很方便。\n3、房子情况：单间转租，湖景房，不带独卫，面积大概10平左右，房子整体装修很新，四室两卫，主卧带有独卫，三户公用卫生间，室友男女皆有，年龄都二十多岁，平时基本见不到面，素质都不错，每月有2次保洁，不用担心公区卫生问题，有厨房可以做饭。\n4、价格：955，押一付一，明年5.22到期，到期可续，可以重新签合同。我现在已经搬走，从今天起到11.21可以送你住，注意⚠️是和中介公司签合同，有小程序平台比较有保障，介意勿扰！\n5、室友在都可以看房，我工作在光谷东不太方便，室友可以帮忙开门，想要看房提前告知约时间！\n6、诚心转租！！中国人不骗中国人！这个房子真的特别好，湖景房超级舒服，在床上看南湖，朝南采光也特别好，太阳可以晒到床上，性价比超高，晚上周围也有小吃，我可以推荐给你！要不是换工作根本不想换，超级值相信我！\n最后最后，中介勿扰！！！     "},{"note_id":"65535346000000001f02f673","cover_url":"https://sns-webpic.xhscdn.com/1040g2sg30rf253o0hk0040tsubj5mdijgn5jeog?imageView2/2/w/540/format/jpg","note_create_time":1699959600,"last_update_time":1699959623,"price":1750,"room_type":4,"keyword":"武汉转租","info":"武汉租房|   光谷创业街一居室转租，1750，押一付三，小区楼下有菜市场，便利店，超市，小区马路对面有小吃一条街，生活便利。附近几百米有佳园路地铁站，有公交站，小区有提车场，交通便利，个人转租，无中介费！无中介费！无中介费！有需要私信，非诚勿扰！"},{"note_id":"6553533d000000000f02bd84","cover_url":"https://sns-webpic.xhscdn.com/1040g00830rf24oi31k004bhafflfureqs47cpj8?imageView2/2/w/540/format/jpg","note_create_time":1699959600,"last_update_time":1699959614,"price":0,"room_type":0,"keyword":"武汉转租","info":"实景实拍 转租，因本人工作变动转租 武汉市|   前进嘉园A区 转租\n欢迎私信"},{"note_id":"655352f400000000320310f0","cover_url":"https://sns-webpic.xhscdn.com/1040g00830rf23rpd1g005paiqjfi5tihek3oi88?imageView2/2/w/540/format/jpg","note_create_time":1699959540,"last_update_time":1699959541,"price":0,"room_type":0,"keyword":"武汉转租","info":"武汉江夏租房的小伙伴看过来哦👀|省心好房，     "},{"note_id":"655351e3000000001f02e9e6","cover_url":"https://sns-webpic.xhscdn.com/1040g2sg30rf1vmi5hk005ooe6ft4g9h9sp7bdf0?imageView2/2/w/540/format/jpg","note_create_time":1699959240,"last_update_time":1699959268,"price":0,"room_type":0,"keyword":"武汉转租","info":"就在光谷～|简直不敢想有多便宜！  "},{"note_id":"655351bd0000000032024e3e","cover_url":"https://sns-webpic.xhscdn.com/1040g00830rf1v2jjh8705n7ttiepbqahe0ksu2g?imageView2/2/w/540/format/jpg","note_create_time":1699959180,"last_update_time":1699959230,"price":0,"room_type":4,"keyword":"武汉转租","info":"武汉转租！中南路，整租，无中介费|我是12.4号到期，但是可以提前搬走，这个可以商量的，也随时可以来看房，我每天都打扫的很干净\n1.一室一卫一厨，42平米左右，厨房不是开放式的不用担心味道的问题，冰箱也有，卫生间配有洗衣机\n2.做饭洗澡有天然气，阳光能照进房间，网费物业费是房东交，电费水费自己用多少交多少，我一般一个月用的电费就十几二十块钱差不多\n3.一栋楼有四个电梯，等电梯不会久比较方便\n4.楼下有很多电动车停车位和充电位，且楼下就是公交站，离四号线地铁站500米，步行几分钟就到了\n5.房间里柜子很多很大，储物空间肯定够，小桌子、全身镜和白色小柜子是我自己准备的，如果有需要可以留着不带走\n6.离武商梦时代、宝通寺、街道口都很近\n7.无中介费手续费啥的杂七杂八的，跟房东直签的       "},{"note_id":"6553512c000000003300ab06","cover_url":"https://sns-webpic.xhscdn.com/1040g00830rf1riq71i004bm4al16krdf99uhvsg?imageView2/2/w/540/format/jpg","note_create_time":1699959060,"last_update_time":1699959084,"price":1270,"room_type":0,"keyword":"武汉转租","info":"文昌路个人转租无中介费|因工作原因不租了 合同五月份到期独卫1270包物业包水费包网费！！无中介费无中介费个人转租！！小区有电梯 小区门口就是公交车站 走10min是文昌路地铁站 近理工大街道口          "},{"note_id":"6553505d000000001100cc78","cover_url":"https://sns-webpic.xhscdn.com/1040g00830rf1pndh18005n2f1tdkardtdgpb3uo?imageView2/2/w/540/format/jpg","note_create_time":1699958820,"last_update_time":1699958878,"price":1150,"room_type":3,"keyword":"武汉转租","info":"武汉转租，中南路，个人转租|武汉转租 中南路 个人转租，主卧阳台房，押一付三1150，有厨房可做饭，楼梯房7楼"},{"note_id":"65534ffb000000003202f698","cover_url":"https://sns-webpic.xhscdn.com/1040g00830rf1nvr1h8604be2n60b1bbdpm1q1vo?imageView2/2/w/540/format/jpg","note_create_time":1699958760,"last_update_time":1699958779,"price":0,"room_type":4,"keyword":"武汉转租","info":"武汉转租！中南路，整租，无中介费|帮转\n我是12.4号到期，但是可以提前搬走，这个可以商量的，也随时可以来看房，我每天都打扫的很干净\n1.一室一卫一厨，42平米左右，厨房不是开放式的不用担心味道的问题，冰箱也有，卫生间配有洗衣机\n2.做饭洗澡有天然气，阳光能照进房间，网费物业费是房东交，电费水费自己用多少交多少，我一般一个月用的电费就十几二十块钱差不多\n3.一栋楼有四个电梯，等电梯不会久比较方便\n4.楼下有很多电动车停车位和充电位，且楼下就是公交站，离四号线地铁站500米，步行几分钟就到了\n5.房间里柜子很多很大，储物空间肯定够，小桌子、全身镜和白色小柜子是我自己准备的，如果有需要可以留着不带走\n6.离武商梦时代、宝通寺、街道口都很近\n7.无中介费手续费啥的杂七杂八的，跟房东直签的\n       "},{"note_id":"65534f1b0000000032003e06","cover_url":"https://sns-webpic.xhscdn.com/1040g2sg30rf1hga71cj05n98cmr48d8uo50bk4g?imageView2/2/w/540/format/jpg","note_create_time":1699958520,"last_update_time":1699958556,"price":0,"room_type":1,"keyword":"武汉转租","info":"转租！！！！光谷大道地铁口单间|因工作变动需要离开武汉，现在转租2号线光谷大道地铁口巴黎豪庭小区单间，室友超好    #转租[话题]"},{"note_id":"65534b5e000000000f029925","cover_url":"https://sns-webpic.xhscdn.com/1040g2sg30rf163i11i005ofe6kq8c7saibk31v8?imageView2/2/w/540/format/jpg","note_create_time":1699957560,"last_update_time":1699957598,"price":0,"room_type":0,"keyword":"武汉转租","info":"龙湖冠寓（杨家湾地铁站店）转租|一居室，包物业 2500，无中介费（如果找冠寓官方签要 3100+）\n酒店式公寓，家电齐全，民水民电。一层7个电梯，通勤不用等半天。\n门禁刷卡、安全性高、物业负责，隔音好。\n缴水电保修什么的都可以直接在 app 上弄，每月一次入户清洁。\n\t\n楼下就有麦当劳，商圈环境好、种类多、去哪都方便\n公寓背面有三个丰巢柜，寄取快递很省心\n公寓可养宠物\n\t\n离杨家湾地铁很近，就在街对面\n  "},{"note_id":"65534a410000000033008d0e","cover_url":"https://sns-webpic.xhscdn.com/1040g2sg30rf10eja1m405n24b3c1sbd5o4tjv8o?imageView2/2/w/540/format/jpg","note_create_time":1699957260,"last_update_time":1699957314,"price":1100,"room_type":1,"keyword":"武汉转租","info":"急转武汉武昌区汉秀旁独立卧室1100押一付一|随时可入住，中南医院，楚河汉街，水果湖高中，省直机关医院附近，电梯房，租期到2024.8.10号，包天然气，网费，水费。独立电表，一块钱一度，需要可以联系我。"},{"note_id":"655348b1000000003200a3a9","cover_url":"https://sns-webpic.xhscdn.com/1040g2sg30rf0rorr1i505p1rj1c3b8bbsr0h058?imageView2/2/w/540/format/jpg","note_create_time":1699956900,"last_update_time":1699956914,"price":1800,"room_type":0,"keyword":"武汉转租","info":"转租武汉一个半月 远洋国际 LOFT|远洋国际 LOFT公寓  转租一个半月\n1800一个月\n一个半月2500元       "},{"note_id":"65536c420000000017034625","cover_url":"https://sns-webpic.xhscdn.com/1040g2sg30rf56mtn18005n92ots4ednib2df96g?imageView2/2/w/540/format/jpg","note_create_time":1699965960,"last_update_time":1699966018,"price":1800,"room_type":0,"keyword":"武汉转租","info":"武汉祥和雅居转租中介勿扰|1800，急租，位置离武汉佳园路地铁站100米，送一个月免费入住，家电齐全，民用水电，带燃气，拎包入住，随时看房，与房东签合同，有意者联系私信   "},{"note_id":"65536c05000000001701ea84","cover_url":"https://sns-webpic.xhscdn.com/1040g00830rf55ke0hm005ngmolvg9ekocl984i0?imageView2/2/w/540/format/jpg","note_create_time":1699965900,"last_update_time":1699965958,"price":0,"room_type":4,"keyword":"武汉转租","info":"武汉汉阳租房❗️❗️不是中介！个人转租～转租！|已经搬走 随时入住\n﻿﻿出租原因：由于工作原因，房子需要转租出去，不是中介，不会收取任何中介费哦。\n﻿﻿本房在31楼电梯房。四室户独门独户互不打扰，这个一居室有窗台晾晒方便，采光很好。\n﻿﻿家电设施：热水器空调桌子椅子厨房冰箱衣柜，单间设施齐全方便。\n﻿水电：独立电表1元一度，季付月付都可以（可以和房东谈）\n﻿﻿位置新城丽景b区，近江腾广场和小吃街，小区门口有便利店水果店餐饮市场超市\n        "},{"note_id":"65536b38000000001b034975","cover_url":"https://sns-webpic.xhscdn.com/1040g00830rf52k3ohk005obparpnvb6tui6paqo?imageView2/2/w/540/format/jpg","note_create_time":1699965720,"last_update_time":1699965753,"price":0,"room_type":4,"keyword":"武汉转租","info":"武汉洪山区杨家湾附近一居室转租|正规一居室转租，房子很干净，因为突发情况现在要转租，价格便宜，房东人也很好，距离地铁站步行十分钟，交通便利，非常适合情侣或者小姐姐居住的房子    "},{"note_id":"65536aa40000000032003e84","cover_url":"https://sns-webpic.xhscdn.com/1040g2sg30rf50cv1hi6g5o66249089506afiupg?imageView2/2/w/540/format/jpg","note_create_time":1699965600,"last_update_time":1699965605,"price":1000,"room_type":0,"keyword":"武汉转租","info":"武汉转租|个人转租千元精装独卫\n环境好，小区安全性高\n但个人准备换工作暂不需要这个房子\n房间够大\n     情侣入住也不是问题"},{"note_id":"65536aa30000000032032674","cover_url":"https://sns-webpic.xhscdn.com/1040g2sg30rf50b5a1c004a35jvhcc0f8o7urqpg?imageView2/2/w/540/format/jpg","note_create_time":1699965600,"last_update_time":1699965603,"price":0,"room_type":4,"keyword":"武汉转租","info":"佳园路地铁口一室一厅转租 燃气热水器|  个人转租 中介勿扰 房东签合同 因个人原因转租 楼下就是夜市  签合同赠送入住天数 只想退个押金回来"},{"note_id":"65536a28000000003103cd26","cover_url":"https://sns-webpic.xhscdn.com/1040g2sg30rf4ufrg1i004a1n8tu16tr2b9fvk8g?imageView2/2/w/540/format/jpg","note_create_time":1699965480,"last_update_time":1699965480,"price":0,"room_type":5,"keyword":"武汉转租","info":"转租啦|中心地段\n距地铁站200m\n2居室\n  "},{"note_id":"655369f7000000001703739d","cover_url":"https://sns-webpic.xhscdn.com/1040g00830rf4tn1ghc005oeoqp8k0jtmveopj7g?imageView2/2/w/540/format/jpg","note_create_time":1699965420,"last_update_time":1699965431,"price":1400,"room_type":3,"keyword":"武汉转租","info":"转租‼️急急‼️急‼️|谁在武汉还没租到房子啊！！!转租！预计12月中旬左右搬走。\n1. 出租原因：由于我个人原因，房子需要转租出去。\n2. 转租的房子：本房在4楼，合租房，小区有电梯，该房间是主卧带独立卫生间。合住室友两男一女，大家都很安静，没有不良习惯。\n3.家电设施：热水器空调桌子椅子冰箱衣柜，单间设\n施一人到两人完全可以，两个人住一起完全不拥挤所以不用担心。\n4. 水电：价格实惠电费燃气费均摊，水费房东负责，一个月电费加燃气费不到八十左右（因为是均摊，没电及时续电费）所以算比较实惠了。\n5. 地址：光谷澎湃城奥山府-8栋-1单元-4层402\n面积14.00，租金1400元/月，出租方式为整租。\n       "},{"note_id":"655369eb000000000f02aa3b","cover_url":"https://sns-webpic.xhscdn.com/1040g2sg30rf4thpuhg6g5obn9p00jhur3ls7sjo?imageView2/2/w/540/format/jpg","note_create_time":1699965360,"last_update_time":1699965517,"price":600,"room_type":0,"keyword":"武汉转租","info":"武汉转租600，无中介费哦，实景实拍|合同2024年5月6号到期，可以免费入住到11月21号，每月600押一付一，位于武昌区丁字桥路向阳佳苑B区，七楼电梯房智能门锁🔒很安全，有洗衣机热水器空调桌椅阳台晾晒，小区内就有便利店和快递站，出小区门口就是公交站，五分钟到中南路地铁站，靠近二号线四号线交通便利，有意向🉑私直接dd，中介鸽子🈚扰🖐🏻       "},{"note_id":"655367db000000001701cd06","cover_url":"https://sns-webpic.xhscdn.com/1040g2sg30rf4lgf51g005ngdgtj0871hajcae98?imageView2/2/w/540/format/jpg","note_create_time":1699964880,"last_update_time":1699964892,"price":1200,"room_type":5,"keyword":"武汉转租","info":"武汉转租|    非中介转租两室一厅单间只租女生 室友也是女生房子的一些信息\n1-位置：水晶郦都（佛祖岭地铁站附近），小区环境好夜跑很安全，附近有公交站、地铁站、有轨电车，有商场，距离湖经小吃街也近\n2-价格：1.2k，无中介费，押一付三、包物业，网费我交了一年可以免费送，民水民电，水电均摊。\n3-房子情况：\n房东直租，两室一厅一厨一卫一阳，实体墙，收纳多，客厅空间足\n冰箱洗衣机燃气都有。室友女生超级好说话很温柔。"},{"note_id":"6553669a0000000032038522","cover_url":"https://sns-webpic.xhscdn.com/1040g00830rf4gjh7hi005nr1rblg83f0bi1t3oo?imageView2/2/w/540/format/jpg","note_create_time":1699964520,"last_update_time":1699964571,"price":870,"room_type":1,"keyword":"武汉转租","info":"个人转租单间，湖口社区|湖口社区～三房一厨一卫～有厨房可做饭\n公交，地铁11号线步行十分钟\n电梯房～单间转租\n价格：870/月\n房屋干净整洁，民水民电\n家具齐全～空调～洗衣机～冰箱～床～衣柜\n生活方便，设施完善，小区附近有超市，饭店，价格实惠\n因朋友工作调动需转租，WiFi免费，水电燃气平摊\n无中介费，男女都可～\n    "},{"note_id":"655362480000000032007cb5","cover_url":"https://sns-webpic.xhscdn.com/1040g00830rf3vo1g1e005nfq61p087nrlsb1i70?imageView2/2/w/540/format/jpg","note_create_time":1699963440,"last_update_time":1699963465,"price":0,"room_type":0,"keyword":"武汉转租","info":"#家人们在线求助 #短租 #武汉光谷租房 #武汉租房#个人转租 #转租 |   #武汉租房 "},{"note_id":"655361870000000032025a07","cover_url":"https://sns-webpic.xhscdn.com/1040g2sg30rf3spb3hi705nqorqig96p1pepn1vg?imageView2/2/w/540/format/jpg","note_create_time":1699963260,"last_update_time":1699963271,"price":850,"room_type":1,"keyword":"武汉转租","info":"武汉洪山区二号线杨家湾地铁口100合租单间大次卧 无中介费 房租850➕30网费|武汉洪山区二号线杨家湾地铁口100合租单间大次卧 无中介费 房租850➕30网费 水费全免 电费用多少交多少，本人这个月15元  爽快的直接送半个月的住宿。  "},{"note_id":"65536053000000001b00cb20","cover_url":"https://sns-webpic.xhscdn.com/1040g00830rf3o25a1g605p6e44iapbb1k6isgbo?imageView2/2/w/540/format/jpg","note_create_time":1699962960,"last_update_time":1699962963,"price":900,"room_type":1,"keyword":"武汉转租","info":"转租 洪山区|洪山区光谷一路成园小区转租 单间外独卫 900一个月\n水费20元每人每月，网费30元一个月，燃气费30元每月（燃气费是需要做饭才交，不做饭不用交），电费独立电表，1块钱每度，物业费每天1块（包含维修） 。\n合同明年9.11到期，最早可以19号，20号入住，最晚11月月底。    "},{"note_id":"65535fb3000000003300b1f8","cover_url":"https://sns-webpic.xhscdn.com/1040g00830rf3lj9th86g5nhrsvd09582728iuoo?imageView2/2/w/540/format/jpg","note_create_time":1699962780,"last_update_time":1699962804,"price":1000,"room_type":1,"keyword":"武汉转租","info":"转租！！欢乐谷附近！近地铁！|谁在武汉还没租到房子啊！个人转租❗️❗️转租❗️预计1月2号左右搬走。\n转租这是一条转租文案\n1．出租原因：由于我个人原因，房子需要转租出去：不是中介，不会收取任何中介费哦。\n2．转租房子的概括：本房在12楼．电梯房．房间外视野广阔。合租，没有公共空间，各自回各自家，环境还可以啦。我这个单 带个大阳台，晾晒方便，采光很好\n3．家电设施：热水器空调桌子椅子衣柜洗衣机，单间设施一人到两人够用两人完全可 两个人住一起完全不拥挤所以不用担心\n4．费用：价格实惠（民水民电），独立电表，月付1000押一付一，转租户主可重新签合同的\n5．位置：林湖景苑，近四号线仁和路，近欢乐谷，上班出行方便，小区门口有便利店水果店餐饮市场超市，    "},{"note_id":"65535ed50000000033002443","cover_url":"https://sns-webpic.xhscdn.com/1040g2sg30rf3i8f7ha005n64gk5k3psqu325n00?imageView2/2/w/540/format/jpg","note_create_time":1699962540,"last_update_time":1699962582,"price":0,"room_type":4,"keyword":"武汉转租","info":"武汉转租|武汉青山区大洲星城A区一居室转租，一手新房，便宜转，有意向私。  "},{"note_id":"65535ca50000000032002df3","cover_url":"https://sns-webpic.xhscdn.com/1040g00830rf39mrd1m005nr0sa2g8kof964mk7g?imageView2/2/w/540/format/jpg","note_create_time":1699962000,"last_update_time":1699962022,"price":0,"room_type":6,"keyword":"武汉转租","info":"转租|临近地铁站，不在市中心，价格不过一千，三室一厅一厨一卫  "},{"note_id":"65535ba00000000032030898","cover_url":"https://sns-webpic.xhscdn.com/1040g00830rf35o4v1i005nr3h9igbh1peu694q0?imageView2/2/w/540/format/jpg","note_create_time":1699961760,"last_update_time":1699961761,"price":0,"room_type":0,"keyword":"武汉转租","info":"转租房子|租金不贵   "},{"note_id":"65535b9400000000330057b2","cover_url":"https://sns-webpic.xhscdn.com/1040g2sg30rf3553vhc005n13g65hp2trcjnr8s0?imageView2/2/w/540/format/jpg","note_create_time":1699961700,"last_update_time":1699961749,"price":0,"room_type":0,"keyword":"武汉转租","info":"梦时代旁武昌个人转租 无中介费包物业宽带|采光好有阳台 无中介费中介勿扰\n包物业包宽带拎包入住\n\t\n送楼下理发店会员卡100元\n我11.18搬走 赠送十天租期   "},{"note_id":"655356fe0000000032037d89","cover_url":"https://sns-webpic.xhscdn.com/1040g2sg30rf2jj3nha005ng20rlg92p5el24ri8?imageView2/2/w/540/format/jpg","note_create_time":1699960560,"last_update_time":1699960575,"price":0,"room_type":4,"keyword":"武汉转租","info":"武汉转租！中南路，整租，无中介费|我是12.4号到期，但是可以提前搬走，这个可以商量的，也随时可以来看房，我每天都打扫的很干净\n1.一室一卫一厨，42平米左右，厨房不是开放式的不用担心味道的问题，冰箱也有，卫生间配有洗衣机\n2.做饭洗澡有天然气，阳光能照进房间，网费物业费是房东交，电费水费自己用多少交多少，我一般一个月用的电费就十几二十块钱差不多\n3.一栋楼有四个电梯，等电梯不会久比较方便\n4.楼下有很多电动车停车位和充电位，且楼下就是公交站，离四号线地铁站500米，步行几分钟就到了\n5.房间里柜子很多很大，储物空间肯定够，小桌子、全身镜和白色小柜子是我自己准备的，如果有需要可以留着不带走\n6.离武商梦时代、宝通寺、街道口都很近，楼下就有宵夜店烧烤店便利店啥的\n7.无中介费手续费啥的杂七杂八的，跟房东直签的\n       "},{"note_id":"65535576000000001f02ffcc","cover_url":"https://sns-webpic.xhscdn.com/1040g00830rf2dlke1e005ogah778ccm12usla6g?imageView2/2/w/540/format/jpg","note_create_time":1699960140,"last_update_time":1699960183,"price":0,"room_type":4,"keyword":"武汉转租","info":"转租一个不要押金的一居室|转租一个不要押金的一居室\n "},{"note_id":"65537ca9000000003203a223","cover_url":"https://sns-webpic.xhscdn.com/1040g2sg30rf76oha1e005nle8lf08198lia1gt0?imageView2/2/w/540/format/jpg","note_create_time":1699970160,"last_update_time":1699970218,"price":1460,"room_type":0,"keyword":"武汉转租","info":"武汉租房|虎泉地铁口转租 合租 带阳台 1460  "},{"note_id":"65537b410000000032001377","cover_url":"https://sns-webpic.xhscdn.com/1040g00830rf70h8b1a005opd163ov2uitj7hf4g?imageView2/2/w/540/format/jpg","note_create_time":1699969800,"last_update_time":1699969858,"price":1100,"room_type":3,"keyword":"武汉转租","info":"个人转租，光谷武汉东站对面，单间，限女生|小区是统建天成美景，武汉东站对面，有2号线和11号线地铁，走路几分钟到地铁站，都是起点站。\n\t\n房子是三室一厅一厨一卫，我租的是主卧，现在不租了要转出去，原本合同跟房东签到明年7月，租金是1100每月，押一付三，含wifi,家电坏了房东负责维修更换。\n另外两间房住的也是女孩，所以只转租给女生，空调洗衣机冰箱都有。\n最好11月20号前可以定下来，房东不允许养宠物哈。\n不是中介，合同也是和房东签的，没有中介费。\n             "},{"note_id":"65537adc000000003202ba40","cover_url":"https://sns-webpic.xhscdn.com/1040g00830rf6vnk5h8kg5o7d9bqg97n2pjnbk7o?imageView2/2/w/540/format/jpg","note_create_time":1699969740,"last_update_time":1699969757,"price":1000,"room_type":1,"keyword":"武汉转租","info":"武汉转租|个人转租千元精装独卫\n环境好，小区安全性高\n房间大 情侣入住不是问题\n个人准备换工作 暂时住不上了   \n电话13035240488"},{"note_id":"655379c20000000032004bb0","cover_url":"https://sns-webpic.xhscdn.com/1040g00830rf6reithk005oo0vd14hposlbfc63o?imageView2/2/w/540/format/jpg","note_create_time":1699969440,"last_update_time":1699969475,"price":0,"room_type":0,"keyword":"武汉转租","info":"个人转租！|因为本人工作原因转租 无中介费！押一付一 🏠合同到明年三月初 阳台房采光好 可和房东直签位于光谷和昌城·逸园 近地铁站800米急出！\n    "},{"note_id":"6553797a000000000f025eb1","cover_url":"https://sns-webpic.xhscdn.com/1040g2sg30rf6q2vnhm005ojt29iodcai1ro5hgo?imageView2/2/w/540/format/jpg","note_create_time":1699969380,"last_update_time":1699969402,"price":1300,"room_type":3,"keyword":"武汉转租","info":"转租，|1300米，藏龙东街地铁口，主卧独卫，只转租给租客，最好独住 "},{"note_id":"6553781900000000170379b7","cover_url":"https://sns-webpic.xhscdn.com/1040g00830rf6ktro1e005nraseo097jv8do8il8?imageView2/2/w/540/format/jpg","note_create_time":1699969020,"last_update_time":1699969050,"price":1000,"room_type":1,"keyword":"武汉转租","info":"古田二路招商江湾转租|旁边就是凯德广场，离地铁也近，招商江湾三室一厅，转租一个小单间，压一付一月租1000，水电自己交，2月份合同到期可以续租，空调洗衣机天然气厨房冰箱都有 "},{"note_id":"655377930000000033004f6f","cover_url":"https://sns-webpic.xhscdn.com/1040g00830rf6itirhie049pdq4l3o06pnu7rbro?imageView2/2/w/540/format/jpg","note_create_time":1699968900,"last_update_time":1699968916,"price":800,"room_type":1,"keyword":"武汉转租","info":"武汉后湖单间800急租|因工作调动需转租，单间八百\n\t\n合租小姐姐性格都很好\n房东年轻人也很好说话\n\t\n对面就是菜市场，地铁口也不远\n目前续租到2024/07/26\n\t\n喜欢戳我👇  "},{"note_id":"65537580000000001100cf2e","cover_url":"https://sns-webpic.xhscdn.com/1040g00830rf6aq3nhg005p0j465ki3jnumfhch0?imageView2/2/w/540/format/jpg","note_create_time":1699968360,"last_update_time":1699968385,"price":1300,"room_type":1,"keyword":"武汉转租","info":"找女室友，光谷软件园(转租群229)|找女室友，光谷软件园\n【房型】:单间\n【小区】:光谷软件园\n【位置】:洪山区关山大道150…\n【价格】:1300 RMB/月\n【合同】:房东\n【余期】:2024-12-12到期\n【短租】:不能\n【付款】:押一付三\n【备注】:正规三居室，带飘窗，朝南次卧，最多三女生合租，不带男友，不养宠物\n    "},{"note_id":"655374d6000000001f02f99b","cover_url":"https://sns-webpic.xhscdn.com/1040g2sg30rf683s418005o1f681g9cktm8k3ht0?imageView2/2/w/540/format/jpg","note_create_time":1699968180,"last_update_time":1699968215,"price":0,"room_type":5,"keyword":"武汉转租","info":"转租！11月9日左右搬走 1.出租原因：因工作调动，房子需要转租出去，不是中介，|转租！11月9日左右搬走\n1.出租原因：因工作调动，房子需要转租出去，不是中介，不收取任何中介费 可以与房东直接签约\n2.房子概括：本房在4楼电梯房，有大窗户采光效果好 两室一厅一卫 民水民电整租\n3.家电设施：热水器 空调 桌子 椅子 沙发 冰箱 微波炉 衣柜 新床 洗衣机\n4.位置：巴黎豪庭 光谷大道地铁口 步行3分钟 楼下有公交车非常方便 适合上班族 楼下超市药店快递站\n   "},{"note_id":"65537296000000001701cd05","cover_url":"https://sns-webpic.xhscdn.com/1040g2sg30rf5tkoj1i0g5n7akkbkj9mfed86kco?imageView2/2/w/540/format/jpg","note_create_time":1699967580,"last_update_time":1699973929,"price":0,"room_type":4,"keyword":"武汉转租","info":"转租｜湖北大学一居室（押一付一，房间已空）|房型为一室一厅一卫一厨+独立阳台，\n位于湖北大学对面，三角花园刘家河小区，\n附近有7号线湖北大学站，3号线三角路站。\n\t\n由于本人工作调动目前急需转租，\n房东直租，无中介费，押一付一，包物业，\n租期到2024年2月15日，到期可以跟房东续签。\n   "},{"note_id":"65537252000000000f028f9a","cover_url":"https://sns-webpic.xhscdn.com/1040g2sg30rf5uavm1m005nle8lf08198265fiq0?imageView2/2/w/540/format/jpg","note_create_time":1699967520,"last_update_time":1699967570,"price":0,"room_type":0,"keyword":"武汉转租","info":"自如租房 虎泉地铁口转租|凯乐桂园合租 带阳台 离二号线地铁口近  "},{"note_id":"6553721e0000000032037322","cover_url":"https://sns-webpic.xhscdn.com/1040g00830rf5tjjb1i5g5odb2fa41nlr92bltr8?imageView2/2/w/540/format/jpg","note_create_time":1699967460,"last_update_time":1699967641,"price":900,"room_type":3,"keyword":"武汉转租","info":"东西湖区合租，找室友| 东建金海湾，找个合租室友，因合租室友工作调动，两室一厅的房子，精装修，家电齐全，有电梯。三店，黄狮海附近。\n主卧出租 900元，压一付三\n "},{"note_id":"655371c6000000001f02ed90","cover_url":"https://sns-webpic.xhscdn.com/1040g00830rf5s74j1k6g5ok9bi7oc29bfamen38?imageView2/2/w/540/format/jpg","note_create_time":1699967400,"last_update_time":1699967530,"price":1050,"room_type":2,"keyword":"武汉转租","info":"光谷软件园附近转租|  \n租金1050元，目前住了两个男生，次卧转租"},{"note_id":"65537167000000003103e33c","cover_url":"https://sns-webpic.xhscdn.com/1040g00830rf5qposhi6g5n36h86kdj2dm5g2ao8?imageView2/2/w/540/format/jpg","note_create_time":1699967280,"last_update_time":1699967336,"price":0,"room_type":0,"keyword":"武汉转租","info":"汉口火车站附近整租个人转租|非中介，需要的私聊  "},{"note_id":"655370f3000000001b036ef0","cover_url":"https://sns-webpic.xhscdn.com/1040g2sg30rf5p1941c005nigqrfg8hecvsbj56g?imageView2/2/w/540/format/jpg","note_create_time":1699967220,"last_update_time":1699967220,"price":0,"room_type":0,"keyword":"武汉转租","info":"个人转租 不要押金|无中介费 无物业费 地址在马房山附近   "},{"note_id":"65537046000000003103df2e","cover_url":"https://sns-webpic.xhscdn.com/1040g2sg30rf5mcv91e6g5p5je4rqp2e0s2adgq0?imageView2/2/w/540/format/jpg","note_create_time":1699967040,"last_update_time":1699967046,"price":0,"room_type":1,"keyword":"武汉转租","info":"谁来租我的房子🏠|   本人因工作原因 就要离开武汉 合同是明年1.1到期 房子是别墅里的一个房间 现在想转租出去 到期了还可以找房东续租 有想法的联系我 房子在江夏庙山 "},{"note_id":"655382c8000000003202701f","cover_url":"https://sns-webpic.xhscdn.com/1040g00830rf7uicj18605o22pegg94r1nirq7cg?imageView2/2/w/540/format/jpg","note_create_time":1699971780,"last_update_time":1699971967,"price":0,"room_type":5,"keyword":"武汉转租","info":"武汉CBD附近两室一厅出租|帮房东大叔转租（大叔人很好）\n整租一套2居室，7楼步梯\n地铁7号线武汉商务区和6号线都不远\n房间內配套齐全，生活足够\n离菜场，超市，公园都很近，生活方便\n附近都是老街坊叔叔阿姨，都很友好\n除了需要爬楼梯其他都很友好\n具体位置在振兴三路合作小区附近    "},{"note_id":"655382790000000033005904","cover_url":"https://sns-webpic.xhscdn.com/1040g2sg30rf7tfn818004a55nhqt7f4v0o81h50?imageView2/2/w/540/format/jpg","note_create_time":1699971660,"last_update_time":1699971706,"price":0,"room_type":0,"keyword":"武汉转租","info":"个人转租|  近app广场  软件园 新发展 保利时代"},{"note_id":"65538199000000003202c2c6","cover_url":"https://sns-webpic.xhscdn.com/1040g2sg30rf7homh18405n8qshr40lcjil7u0vo?imageView2/2/w/540/format/jpg","note_create_time":1699971480,"last_update_time":1699971481,"price":0,"room_type":4,"keyword":"武汉转租","info":"转租一个很喜欢的一楼带院子的 但个人原因要转租.武汉同城欢迎私信#转租 #租房 |转租一个很喜欢的一楼带院子的 但个人原因要转租.武汉同城欢迎私信     "},{"note_id":"65537f7a0000000032036299","cover_url":"https://sns-webpic.xhscdn.com/1040g2sg30rf7homh18005n8qshr40lcj5rqetsg?imageView2/2/w/540/format/jpg","note_create_time":1699970880,"last_update_time":1699970939,"price":0,"room_type":5,"keyword":"武汉转租","info":"一楼一楼一楼 带院子。个人原因转租😭 两室一厅一厨一卫 带院子真的超级舒服.老房|一楼一楼一楼 带院子。个人原因转租😭 两室一厅一厨一卫 带院子真的超级舒服.老房子刚装修完.    "},{"note_id":"65537ef40000000032030594","cover_url":"https://sns-webpic.xhscdn.com/1040g2sg30rf7fmqmhe005p7c4i20a45vhja23sg?imageView2/2/w/540/format/jpg","note_create_time":1699970760,"last_update_time":1699970804,"price":7000,"room_type":0,"keyword":"武汉转租","info":"转租|东原启城转租个人转租合租  东原启城5号线白沙六路地铁站附近上班方便无中介费  物业费我已经交完了 你不需要交了 月付 押一付一拧包入住家具电器一一俱全有个小落地窗 价格7开头 可以养猫哦转租原因:个人因为离上班的地方比较远 想租一个近一点的房子 可私聊"},{"note_id":"65537d940000000033007f68","cover_url":"https://sns-webpic.xhscdn.com/1040g2sg30rf7abii1cdg5ou58u3pupjnt8jf9lo?imageView2/2/w/540/format/jpg","note_create_time":1699970400,"last_update_time":1699973624,"price":0,"room_type":7,"keyword":"武汉转租","info":"武汉光谷五路，转租|时间：11.19\n可三个月短租，签的一年合同，目前租金维持还剩一个月，也可以转租我的，三个月短租不收押金。四居室，靠近沃德中心，华翔中心，小米。\n地点：武汉绿地光谷中心城 \n拎包入住，有厨房"}]